Workbook

Sheet Backlog
A1: EPIC | B1: ID User Story | C1: Libellé User Story | D1: MVP | E1: Front_or_Back | F1: Module | G1: Dépend de (Parent) | H1: Type fonctionnel | I1: Pilier(s) | J1: Profil utilisateur | K1: Phrase méthode agile | L1: Point d'effort prestataire | M1: Point d'effort estimé MOA
A2: EPIC 1 – Gestion des données | B2: US1.1 | C2: Importer des données via fichier | D2: True | E2: Front-end | F2: Gestion des données & catalogue | H2: Acquisition | I2: Pilier 1 – Connaissance & Caractérisation | J2: Administrateur expert data | K2: En tant qu'administrateur expert data, je veux importer des données via fichier afin que la plateforme dispose de données fiables et homogènes. | L2: 12 | M2: 22
A3: EPIC 1 – Gestion des données | B3: US1.2 | C3: Connecter une API externe | D3: False | E3: Front-end | F3: Gestion des données & catalogue | H3: Acquisition | I3: Pilier 1 – Connaissance & Caractérisation | J3: Administrateur expert data | K3: En tant qu'administrateur expert data, je veux connecter une API externe afin d'alimenter la plateforme sans fichier.
A4: EPIC 1 – Gestion des données | B4: US1.3 | C4: Planifier des imports simples | D4: True | E4: Backend | F4: Gestion des données & catalogue | G4: US1.1 | H4: Acquisition | I4: Pilier 1 – Connaissance & Caractérisation | J4: Administrateur expert data | K4: En tant qu'administrateur expert data, je veux planifier des imports simples afin que les données soient actualisées automatiquement. | L4: =SUMIF('Besoins testables'!$D:$D,$A4,'Besoins testables'!$O:$O) -> 0
A5: EPIC 1 – Gestion des données | B5: US1.4 | C5: Normaliser les données | D5: True | E5: Backend | F5: Gestion des données & catalogue | G5: US1.1 | H5: Structuration | I5: Pilier 1 – Connaissance & Caractérisation | J5: Administrateur expert data | K5: En tant qu'administrateur expert data, je veux normaliser les données afin qu'elles soient homogènes et comparables. | L5: =SUMIF('Besoins testables'!$D:$D,$A5,'Besoins testables'!$O:$O) -> 0
A6: EPIC 1 – Gestion des données | B6: US1.5 | C6: Gérer les erreurs d'import | D6: True | E6: Front-end | F6: Gestion des données & catalogue | G6: US1.1 | H6: Acquisition | I6: Pilier 1 – Connaissance & Caractérisation | J6: Administrateur expert data | K6: En tant qu'administrateur expert data, je veux gérer les erreurs d'import afin de corriger les données rejetées efficacement. | L6: =SUMIF('Besoins testables'!$D:$D,$A6,'Besoins testables'!$O:$O) -> 0
A7: EPIC 1 – Gestion des données | B7: US1.6 | C7: Historiser les données | D7: True | E7: Backend | F7: Gestion des données & catalogue | G7: US1.1 | H7: Gouvernance | I7: Transverse (socle) | J7: Administrateur expert data | K7: En tant qu'administrateur expert data, je veux historiser les données afin de reconstituer leur évolution dans le temps. | L7: =SUMIF('Besoins testables'!$D:$D,$A7,'Besoins testables'!$O:$O) -> 0
A8: EPIC 1 – Gestion des données | B8: US1.7 | C8: Rejouer un traitement | D8: False | E8: Backend | F8: Gestion des données & catalogue | H8: Acquisition | I8: Pilier 1 – Connaissance & Caractérisation | J8: Administrateur expert data | K8: En tant qu'administrateur expert data, je veux rejouer un traitement afin de recalculer un jeu de données après correction.
A9: EPIC 1bis – Catalogage des données | B9: US1bis.1 | C9: Enregistrer un jeu de données dans le catalogue | D9: True | E9: Front-end | F9: Gestion des données & catalogue | G9: US1.2 | H9: Structuration | I9: Pilier 1 – Connaissance & Caractérisation | J9: Administrateur expert data | K9: En tant qu'administrateur expert data, je veux enregistrer un jeu de données dans le catalogue afin qu'il soit référencé et trouvable. | L9: =SUMIF('Besoins testables'!$D:$D,$A9,'Besoins testables'!$O:$O) -> 0
A10: EPIC 1bis – Catalogage des données | B10: US1bis.2 | C10: Associer des métadonnées à un jeu de données | D10: True | E10: Front-end | F10: Gestion des données & catalogue | G10: US1bis.1 | H10: Structuration | I10: Pilier 1 – Connaissance & Caractérisation | J10: Administrateur expert data | K10: En tant qu'administrateur expert data, je veux associer des métadonnées à un jeu de données afin d'en documenter l'origine et la structure. | L10: =SUMIF('Besoins testables'!$D:$D,$A10,'Besoins testables'!$O:$O) -> 0
A11: EPIC 1bis – Catalogage des données | B11: US1bis.3 | C11: Modifier les métadonnées d'un jeu de données | D11: False | E11: Front-end | F11: Gestion des données & catalogue | G11: US1bis.2 | H11: Structuration | I11: Pilier 1 – Connaissance & Caractérisation | J11: Administrateur expert data | K11: En tant qu'administrateur expert data, je veux modifier les métadonnées afin de maintenir le catalogue à jour.
A12: EPIC 1bis – Catalogage des données | B12: US1bis.4 | C12: Consulter les informations d'un jeu de données | D12: True | E12: Front-end | F12: Gestion des données & catalogue | H12: Structuration | I12: Pilier 1 – Connaissance & Caractérisation | J12: Administrateur expert data | K12: En tant qu'administrateur expert data, je veux consulter les informations d'un jeu de données afin d'en connaître le contenu et la source. | L12: =SUMIF('Besoins testables'!$D:$D,$A12,'Besoins testables'!$O:$O) -> 0
A13: EPIC 1bis – Catalogage des données | B13: US1bis.5 | C13: Rechercher un jeu de données dans le catalogue | D13: False | E13: Front-end | F13: Gestion des données & catalogue | H13: Structuration | I13: Pilier 1 – Connaissance & Caractérisation | J13: Administrateur expert data | K13: En tant qu'administrateur expert data, je veux rechercher un jeu de données afin de le retrouver rapidement dans le catalogue.
A14: EPIC 1bis – Catalogage des données | B14: US1bis.6 | C14: Filtrer les jeux de données selon des critères | D14: False | E14: Front-end | F14: Gestion des données & catalogue | H14: Structuration | I14: Pilier 1 – Connaissance & Caractérisation | J14: Administrateur expert data | K14: En tant qu'administrateur expert data, je veux filtrer les jeux de données selon des critères afin de restreindre la liste du catalogue.
A15: EPIC 1bis – Catalogage des données | B15: US1bis.7 | C15: Visualiser les relations entre indicateur et données sources | D15: True | E15: Front-end | F15: Gestion des données & catalogue | H15: Structuration | I15: Pilier 1 – Connaissance & Caractérisation | J15: Administrateur expert data | K15: En tant qu'administrateur expert data, je veux visualiser les relations entre un indicateur et ses données sources afin d'en comprendre la provenance. | L15: =SUMIF('Besoins testables'!$D:$D,$A15,'Besoins testables'!$O:$O) -> 0
A16: EPIC 1bis – Catalogage des données | B16: US1bis.8 | C16: Tracer les transformations appliquées à un jeu de données | D16: False | E16: Backend | F16: Gestion des données & catalogue | H16: Structuration | I16: Pilier 1 – Connaissance & Caractérisation | J16: Administrateur expert data | K16: En tant qu'administrateur expert data, je veux tracer les transformations appliquées à un jeu de données afin d'en garantir la reproductibilité.
A17: EPIC 1bis – Catalogage des données | B17: US1bis.9 | C17: Identifier une donnée comme source ou dérivée | D17: False | E17: Backend | F17: Gestion des données & catalogue | H17: Structuration | I17: Pilier 1 – Connaissance & Caractérisation | J17: Administrateur expert data | K17: En tant qu'administrateur expert data, je veux identifier une donnée comme source ou dérivée afin de clarifier sa place dans la chaîne.
A18: EPIC 1bis – Catalogage des données | B18: US1bis.10 | C18: Alimenter automatiquement le catalogue lors des imports | D18: True | E18: Backend | F18: Gestion des données & catalogue | G18: US1.1 ; US1bis.1 | H18: Acquisition | I18: Pilier 1 – Connaissance & Caractérisation | J18: Administrateur expert data | K18: En tant qu'administrateur expert data, je veux alimenter automatiquement le catalogue lors des imports afin d'éviter les saisies manuelles. | L18: =SUMIF('Besoins testables'!$D:$D,$A18,'Besoins testables'!$O:$O) -> 0
A19: EPIC 1bis – Catalogage des données | B19: US1bis.11 | C19: Relier un jeu de données à un traitement (ex : dbt) | D19: False | E19: Backend | F19: Gestion des données & catalogue | G19: US1bis.8 | H19: Structuration | I19: Pilier 1 – Connaissance & Caractérisation | J19: Administrateur expert data | K19: En tant qu'administrateur expert data, je veux relier un jeu de données à un traitement afin d'en retracer l'élaboration.
A20: EPIC 1bis – Catalogage des données | B20: US1bis.12 | C20: Enregistrer un indicateur comme donnée dérivée | D20: True | E20: Front-end | F20: Gestion des données & catalogue | G20: US3.5 | H20: Structuration | I20: Pilier 1 – Connaissance & Caractérisation | J20: Administrateur expert data | K20: En tant qu'administrateur expert data, je veux enregistrer un indicateur comme donnée dérivée afin qu'il soit identifié comme tel dans le catalogue. | L20: =SUMIF('Besoins testables'!$D:$D,$A20,'Besoins testables'!$O:$O) -> 0
A21: EPIC 1bis – Catalogage des données | B21: US1bis.13 | C21: Consulter les métadonnées d'un indicateur | D21: False | E21: Front-end | F21: Gestion des données & catalogue | H21: Structuration | I21: Pilier 1 – Connaissance & Caractérisation | J21: Administrateur expert data | K21: En tant qu'administrateur expert data, je veux consulter les métadonnées d'un indicateur afin d'en vérifier la définition et la méthode.
A22: EPIC 1bis – Catalogage des données | B22: US1bis.14 | C22: Ajouter un nouveau jeu de données sans modifier la structure | D22: False | E22: Backend | F22: Gestion des données & catalogue | H22: Structuration | I22: Pilier 1 – Connaissance & Caractérisation | J22: Administrateur expert data | K22: En tant qu'administrateur expert data, je veux ajouter un nouveau jeu de données sans modifier la structure afin d'étendre le catalogue à moindre coût.
A23: EPIC 1bis – Catalogage des données | B23: US1bis.15 | C23: Historiser les modifications des métadonnées | D23: False | E23: Backend | F23: Gestion des données & catalogue | H23: Structuration | I23: Pilier 1 – Connaissance & Caractérisation | J23: Administrateur expert data | K23: En tant qu'administrateur expert data, je veux historiser les modifications des métadonnées afin de tracer les évolutions du catalogue.
A24: EPIC 2 – Qualité des données | B24: US2.1 | C24: Détecter des valeurs aberrantes | D24: True | E24: Backend | F24: Suivi qualité & traçabilité | H24: Qualification | I24: Pilier 1 – Connaissance & Caractérisation (fondement) | J24: Administrateur expert data | K24: En tant qu'administrateur expert data, je veux détecter des valeurs aberrantes afin d'identifier les données à corriger. | L24: =SUMIF('Besoins testables'!$D:$D,$A24,'Besoins testables'!$O:$O) -> 0
A25: EPIC 2 – Qualité des données | B25: US2.2 | C25: Vérifier cohérence temporelle | D25: False | E25: Backend | F25: Suivi qualité & traçabilité | H25: Qualification | I25: Pilier 1 – Connaissance & Caractérisation (fondement) | J25: Administrateur expert data | K25: En tant qu'administrateur expert data, je veux vérifier la cohérence temporelle afin de détecter les incohérences de dates.
A26: EPIC 2 – Qualité des données | B26: US2.3 | C26: Vérifier cohérence spatiale | D26: False | E26: Backend | F26: Suivi qualité & traçabilité | H26: Qualification | I26: Pilier 1 – Connaissance & Caractérisation (fondement) | J26: Administrateur expert data | K26: En tant qu'administrateur expert data, je veux vérifier la cohérence spatiale afin de détecter les incohérences géographiques. | L26: =SUMIF('Besoins testables'!$D:$D,$A26,'Besoins testables'!$O:$O) -> 0
A27: EPIC 2 – Qualité des données | B27: US2.4 | C27: Calculer un taux de complétude | D27: True | E27: Backend | F27: Suivi qualité & traçabilité | H27: Qualification | I27: Pilier 1 – Connaissance & Caractérisation (fondement) | J27: Administrateur expert data | K27: En tant qu'administrateur expert data, je veux calculer un taux de complétude afin de mesurer la couverture des données. | L27: =SUMIF('Besoins testables'!$D:$D,$A27,'Besoins testables'!$O:$O) -> 0
A28: EPIC 2 – Qualité des données | B28: US2.5 | C28: Qualifier la fiabilité | D28: True | E28: Backend | F28: Suivi qualité & traçabilité | H28: Qualification | I28: Pilier 1 – Connaissance & Caractérisation (fondement) | J28: Administrateur expert data | K28: En tant qu'administrateur expert data, je veux qualifier la fiabilité afin d'évaluer la confiance à accorder aux données. | L28: =SUMIF('Besoins testables'!$D:$D,$A28,'Besoins testables'!$O:$O) -> 0
A29: EPIC 2 – Qualité des données | B29: US2.6 | C29: Associer des métadonnées | D29: True | E29: Front-end | F29: Suivi qualité & traçabilité | H29: Qualification | I29: Pilier 1 – Connaissance & Caractérisation (fondement) | J29: Administrateur expert data | K29: En tant qu'administrateur expert data, je veux associer des métadonnées de qualité afin de documenter les contrôles effectués. | L29: =SUMIF('Besoins testables'!$D:$D,$A29,'Besoins testables'!$O:$O) -> 0
A30: EPIC 2 – Qualité des données | B30: US2.7 | C30: Visualiser la qualité | D30: False | E30: Front-end | F30: Suivi qualité & traçabilité | H30: Qualification | I30: Pilier 1 – Connaissance & Caractérisation (fondement) | J30: Administrateur expert data | K30: En tant qu'administrateur expert data, je veux visualiser la qualité afin de repérer les jeux de données fiables.
A31: EPIC 3 – Référentiels | B31: US3.1 | C31: Gérer les bassins versants | D31: True | E31: Front-end | F31: Administration & profils | H31: Structuration | I31: Pilier 1 – Connaissance & Caractérisation | J31: Administrateur expert data | K31: En tant qu'administrateur expert data, je veux gérer les bassins versants afin de maintenir le référentiel à jour. | L31: =SUMIF('Besoins testables'!$D:$D,$A31,'Besoins testables'!$O:$O) -> 0
A32: EPIC 3 – Référentiels | B32: US3.2 | C32: Gérer les captages | D32: True | E32: Front-end | F32: Administration & profils | H32: Structuration | I32: Pilier 1 – Connaissance & Caractérisation | J32: Administrateur expert data | K32: En tant qu'administrateur expert data, je veux gérer les captages afin de maintenir le référentiel à jour. | L32: =SUMIF('Besoins testables'!$D:$D,$A32,'Besoins testables'!$O:$O) -> 0
A33: EPIC 3 – Référentiels | B33: US3.3 | C33: Gérer périmètres de protection | D33: False | E33: Front-end | F33: Administration & profils | H33: Structuration | I33: Pilier 1 – Connaissance & Caractérisation | J33: Administrateur expert data | K33: En tant qu'administrateur expert data, je veux gérer les périmètres de protection afin de les représenter sur la carte.
A34: EPIC 3 – Référentiels | B34: US3.4 | C34: Gérer la maille H3 | D34: True | E34: Front-end | F34: Administration & profils | H34: Structuration | I34: Pilier 1 – Connaissance & Caractérisation | J34: Administrateur expert data | K34: En tant qu'administrateur expert data, je veux gérer la maille H3 afin de garantir la cohérence des agrégations. | L34: =SUMIF('Besoins testables'!$D:$D,$A34,'Besoins testables'!$O:$O) -> 0
A35: EPIC 3 – Référentiels | B35: US3.5 | C35: Définir un indicateur | D35: True | E35: Front-end | F35: Administration & profils | H35: Structuration | I35: Pilier 1 – Connaissance & Caractérisation | J35: Administrateur expert data | K35: En tant qu'administrateur expert data, je veux définir un indicateur afin de le rendre calculable et affichable. | L35: =SUMIF('Besoins testables'!$D:$D,$A35,'Besoins testables'!$O:$O) -> 0
A36: EPIC 3 – Référentiels | B36: US3.6 | C36: Gérer les profils utilisateurs | D36: False | E36: Front-end | F36: Administration & profils | H36: Gouvernance | I36: Transverse (socle) | J36: Administrateur plateforme | K36: En tant qu'administrateur plateforme, je veux gérer les profils utilisateurs et leurs droits afin de contrôler les accès à la plateforme.
A37: EPIC 3 – Référentiels | B37: US3.7 | C37: Versionner les référentiels | D37: False | E37: Backend | F37: Administration & profils | H37: Structuration | I37: Pilier 1 – Connaissance & Caractérisation | J37: Administrateur expert data | K37: En tant qu'administrateur expert data, je veux versionner les référentiels afin de conserver l'historique de leurs évolutions.
A38: EPIC 4 – Calcul d'indicateurs | B38: US4.1 | C38: Calculer des indicateurs simples | D38: True | E38: Backend | F38: Gestion des données & catalogue | G38: US3.5 ; US4.7 ; US1bis.12 | H38: Exploitation | I38: Pilier 2 – Diagnostic & Analyse multicritère (+ Pilier 3) | J38: Administrateur expert data | K38: En tant qu'administrateur expert data, je veux calculer des indicateurs simples afin de produire des valeurs fiables. | L38: =SUMIF('Besoins testables'!$D:$D,$A38,'Besoins testables'!$O:$O) -> 0
A39: EPIC 4 – Calcul d'indicateurs | B39: US4.2 | C39: Agréger à l'échelle BV | D39: True | E39: Backend | F39: Gestion des données & catalogue | G39: US3.1 ; US4.1 | H39: Exploitation | I39: Pilier 2 – Diagnostic & Analyse multicritère (+ Pilier 3) | J39: Administrateur expert data | K39: En tant qu'administrateur expert data, je veux agréger à l'échelle du bassin versant afin de disposer de valeurs synthétiques. | L39: =SUMIF('Besoins testables'!$D:$D,$A39,'Besoins testables'!$O:$O) -> 0
A40: EPIC 4 – Calcul d'indicateurs | B40: US4.3 | C40: Agrégation temporelle | D40: True | E40: Backend | F40: Gestion des données & catalogue | G40: US1.6 ; US4.1 ; US6.24 | H40: Exploitation | I40: Pilier 2 – Diagnostic & Analyse multicritère (+ Pilier 3) | J40: Administrateur expert data | K40: En tant qu'administrateur expert data, je veux agréger les données dans le temps afin de produire des séries comparables. | L40: =SUMIF('Besoins testables'!$D:$D,$A40,'Besoins testables'!$O:$O) -> 0
A41: EPIC 4 – Calcul d'indicateurs | B41: US4.4 | C41: Paramétrer un calcul | D41: False | E41: Backend | F41: Gestion des données & catalogue | H41: Exploitation | I41: Pilier 2 – Diagnostic & Analyse multicritère (+ Pilier 3) | J41: Administrateur expert data | K41: En tant qu'administrateur expert data, je veux paramétrer un calcul afin d'ajuster les règles de production de l'indicateur.
A42: EPIC 4 – Calcul d'indicateurs | B42: US4.5 | C42: Filtrer les données | D42: True | E42: Front-end | F42: Gestion des données & catalogue | H42: Exploitation | I42: Pilier 2 – Diagnostic & Analyse multicritère (+ Pilier 3) | J42: Administrateur expert data | K42: En tant qu'administrateur expert data, je veux filtrer les données afin de restreindre le calcul aux valeurs pertinentes. | L42: =SUMIF('Besoins testables'!$D:$D,$A42,'Besoins testables'!$O:$O) -> 0
A43: EPIC 4 – Calcul d'indicateurs | B43: US4.6 | C43: Versionner un indicateur | D43: False | E43: Backend | F43: Gestion des données & catalogue | H43: Exploitation | I43: Pilier 2 – Diagnostic & Analyse multicritère (+ Pilier 3) | J43: Administrateur expert data | K43: En tant qu'administrateur expert data, je veux versionner un indicateur afin de conserver la traçabilité de ses évolutions.
A44: EPIC 4 – Calcul d'indicateurs | B44: US4.7 | C44: Recalculer un indicateur | D44: False | E44: Backend | F44: Gestion des données & catalogue | G44: US4.1 | H44: Exploitation | I44: Pilier 2 – Diagnostic & Analyse multicritère (+ Pilier 3) | J44: Administrateur expert data | K44: En tant qu'administrateur expert data, je veux recalculer un indicateur afin de mettre à jour les valeurs après correction.
A45: EPIC 5 – Analyse multicritère | B45: US5.1 | C45: Construire un indice composite | D45: False | E45: Front-end | F45: Suivi & veille | G45: US4.1 | H45: Exploitation | I45: Pilier 2 – Diagnostic & Analyse multicritère (+ Pilier 3) | J45: Administrateur expert data | K45: En tant qu'administrateur expert data, je veux construire un indice composite afin de fournir une base transparente pour l'aide à la décision.
A46: EPIC 5 – Analyse multicritère | B46: US5.2 | C46: Définir des pondérations | D46: False | E46: Front-end | F46: Suivi & veille | G46: US5.1 | H46: Exploitation | I46: Pilier 2 – Diagnostic & Analyse multicritère (+ Pilier 3) | J46: Expert métier eau potable | K46: En tant qu'expert métier eau potable, je veux définir les pondérations de l'analyse multicritère afin d'évaluer le risque réel de dégradation de la ressource.
A47: EPIC 5 – Analyse multicritère | B47: US5.3 | C47: Tester des scénarios | D47: False | E47: Front-end | F47: Suivi & veille | G47: US5.1 ; US5.2 | H47: Exploitation | I47: Pilier 2 – Diagnostic & Analyse multicritère (+ Pilier 3) | J47: Expert métier eau potable | K47: En tant qu'expert métier eau potable, je veux tester des scénarios de pondération afin d'analyser l'impact des différents facteurs sur le classement de criticité.
A48: EPIC 5 – Analyse multicritère | B48: US5.4 | C48: Comparer scénarios | D48: False | E48: Front-end | F48: Suivi & veille | G48: US5.1 ; US5.3 | H48: Exploitation | I48: Pilier 2 – Diagnostic & Analyse multicritère (+ Pilier 3) | J48: Expert métier eau potable | K48: En tant qu'expert métier eau potable, je veux comparer les scénarios de l'analyse multicritère afin d'identifier la pondération la plus représentative du terrain.
A49: EPIC 5 – Analyse multicritère | B49: US5.5 | C49: Visualiser contributions | D49: False | E49: Front-end | F49: Suivi & veille | G49: US5.1 ; US5.3 ; US5.4 | H49: Exploitation | I49: Pilier 2 – Diagnostic & Analyse multicritère (+ Pilier 3) | J49: Expert métier eau potable | K49: En tant qu'expert métier eau potable, je veux visualiser la contribution de chaque indicateur au score de criticité afin de comprendre les facteurs de risque dominants.
A50: EPIC 5 – Analyse multicritère | B50: US5.6 | C50: Documenter méthodes | D50: False | E50: Backend | F50: Suivi & veille | H50: Exploitation | I50: Pilier 2 – Diagnostic & Analyse multicritère (+ Pilier 3) | J50: Administrateur expert data | K50: En tant qu'administrateur expert data, je veux documenter les méthodes de calcul afin d'assurer la transparence de l'aide à la décision.
A51: EPIC 6 – Visualisation | B51: US6.1 | C51: Visualiser sur carte | D51: True | E51: Front-end | F51: Cartographie & exploration > Cartographie | H51: Restitution – Diffusion | I51: Pilier 4 – Partage & Diffusion | J51: Intéressé public | K51: En tant qu'intéressé public, je veux visualiser les données sur carte afin de situer les territoires concernés. | L51: =SUMIF('Besoins testables'!$D:$D,$A51,'Besoins testables'!$O:$O) -> 0
A52: EPIC 6 – Visualisation | B52: US6.2 | C52: Afficher indicateurs carto | D52: True | E52: Front-end | F52: Cartographie & exploration > Cartographie | G52: US3.5 | H52: Restitution – Diffusion | I52: Pilier 4 – Partage & Diffusion | J52: Intéressé public | K52: En tant qu'intéressé public, je veux afficher les indicateurs sur la carte afin d'en lire la répartition géographique. | L52: =SUMIF('Besoins testables'!$D:$D,$A52,'Besoins testables'!$O:$O) -> 0
A53: EPIC 6 – Visualisation | B53: US6.3 | C53: Navigation (zoom filtres) | D53: True | E53: Front-end | F53: Cartographie & exploration > Cartographie | H53: Restitution – Diffusion | I53: Pilier 4 – Partage & Diffusion | J53: Intéressé public | K53: En tant qu'intéressé public, je veux naviguer sur la carte afin d'explorer librement le territoire. | L53: =SUMIF('Besoins testables'!$D:$D,$A53,'Besoins testables'!$O:$O) -> 0
A54: EPIC 6 – Visualisation | B54: US6.4 | C54: Graphiques temporels | D54: True | E54: Front-end | F54: Cartographie & exploration > Visualisation & dataviz | G54: US6.7 | H54: Restitution – Diffusion | I54: Pilier 4 – Partage & Diffusion | J54: Expert métier eau potable | K54: En tant qu'expert métier eau potable, je veux consulter l'évolution temporelle des indicateurs afin d'identifier les dynamiques impactant la ressource. | L54: =SUMIF('Besoins testables'!$D:$D,$A54,'Besoins testables'!$O:$O) -> 0
A55: EPIC 6 – Visualisation | B55: US6.5 | C55: Comparer territoires | D55: False | E55: Front-end | F55: Cartographie & exploration > Visualisation & dataviz | H55: Restitution – Diffusion | I55: Pilier 4 – Partage & Diffusion | J55: Décideur métier | K55: En tant que décideur métier, je veux comparer des territoires afin d'arbitrer les investissements.
A56: EPIC 6 – Visualisation | B56: US6.6 | C56: Tableau de bord avancé | D56: False | E56: Front-end | F56: Cartographie & exploration > Visualisation & dataviz | H56: Restitution – Diffusion | I56: Pilier 4 – Partage & Diffusion | J56: Décideur métier | K56: En tant que décideur métier, je veux disposer d'un tableau de bord avancé afin d'avoir une vue agrégée de l'information.
A57: EPIC 6 – Visualisation | B57: US6.7 | C57: Fiche territoire | D57: True | E57: Front-end | F57: Cartographie & exploration > Fiches & synthèse territoriale | H57: Restitution – Diffusion | I57: Pilier 4 – Partage & Diffusion | J57: Décideur métier | K57: En tant que décideur métier, je veux consulter une fiche territoire afin d'avoir une synthèse d'un bassin versant. | L57: =SUMIF('Besoins testables'!$D:$D,$A57,'Besoins testables'!$O:$O) -> 0
A58: EPIC 6 – Visualisation | B58: US6.8 | C58: Basculer l'échelle d'analyse Captages ↔ Bassins versants | D58: True | E58: Front-end | F58: Cartographie & exploration > Cartographie | G58: US3.1 ; US3.2 | H58: Restitution – Diffusion | I58: Pilier 4 – Partage & Diffusion | J58: Administrateur expert data | K58: En tant qu'administrateur expert data, je veux basculer l'échelle d'analyse entre captages et bassins versants afin de changer de niveau de lecture. | L58: =SUMIF('Besoins testables'!$D:$D,$A58,'Besoins testables'!$O:$O) -> 0
A59: EPIC 6 – Visualisation | B59: US6.9 | C59: Afficher le compteur d'unités sélectionnées | D59: True | E59: Front-end | F59: Cartographie & exploration > Outils d'exploration | H59: Restitution – Diffusion | I59: Pilier 4 – Partage & Diffusion | J59: Intéressé public | K59: En tant qu'intéressé public, je veux afficher le compteur d'unités sélectionnées afin de connaître le périmètre courant. | L59: =SUMIF('Besoins testables'!$D:$D,$A59,'Besoins testables'!$O:$O) -> 0
A60: EPIC 6 – Visualisation | B60: US6.10 | C60: Rechercher avec suggestions (commune, province, captage, presets) | D60: True | E60: Front-end | F60: Cartographie & exploration > Sélecteur de captages / BV | H60: Restitution – Diffusion | I60: Pilier 4 – Partage & Diffusion | J60: Intéressé public | K60: En tant qu'intéressé public, je veux rechercher avec des suggestions afin de trouver rapidement un captage ou une commune. | L60: =SUMIF('Besoins testables'!$D:$D,$A60,'Besoins testables'!$O:$O) -> 0
A61: EPIC 6 – Visualisation | B61: US6.11 | C61: Cumuler plusieurs facettes de recherche (sélection multiple) | D61: True | E61: Front-end | F61: Cartographie & exploration > Sélecteur de captages / BV | H61: Restitution – Diffusion | I61: Pilier 4 – Partage & Diffusion | J61: Intéressé public | K61: En tant qu'intéressé public, je veux cumuler plusieurs facettes de recherche afin d'affiner ma sélection. | L61: =SUMIF('Besoins testables'!$D:$D,$A61,'Besoins testables'!$O:$O) -> 0
A62: EPIC 6 – Visualisation | B62: US6.12 | C62: Afficher les facettes actives en puces décochables (SOLR/CKAN) | D62: True | E62: Front-end | F62: Cartographie & exploration > Outils d'exploration | H62: Restitution – Diffusion | I62: Pilier 4 – Partage & Diffusion | J62: Intéressé public | K62: En tant qu'intéressé public, je veux voir les facettes actives en puces afin de savoir quels filtres sont appliqués. | L62: =SUMIF('Besoins testables'!$D:$D,$A62,'Besoins testables'!$O:$O) -> 0
A63: EPIC 6 – Visualisation | B63: US6.13 | C63: Appliquer un preset « Top 10 » (plus/moins exposés, plus/moins proches) et pouvoir le retirer | D63: True | E63: Front-end | F63: Cartographie & exploration > Sélecteur de captages / BV | H63: Restitution – Diffusion | I63: Pilier 4 – Partage & Diffusion | J63: Intéressé public | K63: En tant qu'intéressé public, je veux appliquer un preset afin d'afficher rapidement les territoires les plus concernés. | L63: =SUMIF('Besoins testables'!$D:$D,$A63,'Besoins testables'!$O:$O) -> 0
A64: EPIC 6 – Visualisation | B64: US6.14 | C64: Décocher une facette pour retirer filtre ou sélection | D64: True | E64: Front-end | F64: Cartographie & exploration > Outils d'exploration | H64: Restitution – Diffusion | I64: Pilier 4 – Partage & Diffusion | J64: Intéressé public | K64: En tant qu'intéressé public, je veux décocher une facette afin de retirer un filtre en un clic. | L64: =SUMIF('Besoins testables'!$D:$D,$A64,'Besoins testables'!$O:$O) -> 0
A65: EPIC 6 – Visualisation | B65: US6.15 | C65: Sélectionner / désélectionner / retirer une unité individuellement | D65: True | E65: Front-end | F65: Cartographie & exploration > Sélecteur de captages / BV | H65: Restitution – Diffusion | I65: Pilier 4 – Partage & Diffusion | J65: Intéressé public | K65: En tant qu'intéressé public, je veux sélectionner ou retirer une unité individuellement afin de personnaliser ma sélection. | L65: =SUMIF('Besoins testables'!$D:$D,$A65,'Besoins testables'!$O:$O) -> 0
A66: EPIC 6 – Visualisation | B66: US6.16 | C66: Conserver indépendamment les sélections Captages et Bassins versants | D66: True | E66: Front-end | F66: Cartographie & exploration > Sélecteur de captages / BV | H66: Restitution – Diffusion | I66: Pilier 4 – Partage & Diffusion | J66: Administrateur expert data | K66: En tant qu'administrateur expert data, je veux conserver indépendamment les sélections captages et bassins versants afin de ne pas les mélanger. | L66: =SUMIF('Besoins testables'!$D:$D,$A66,'Besoins testables'!$O:$O) -> 0
A67: EPIC 6 – Visualisation | B67: US6.17 | C67: Trier la liste (distance / nom) | D67: True | E67: Front-end | F67: Cartographie & exploration > Sélecteur de captages / BV | H67: Restitution – Diffusion | I67: Pilier 4 – Partage & Diffusion | J67: Intéressé public | K67: En tant qu'intéressé public, je veux trier la liste par distance ou par nom afin d'organiser ma lecture. | L67: =SUMIF('Besoins testables'!$D:$D,$A67,'Besoins testables'!$O:$O) -> 0
A68: EPIC 6 – Visualisation | B68: US6.18 | C68: Calculer les communes intersectant un BV (≥ 20 %) pour la facette Commune | D68: True | E68: Backend | F68: Cartographie & exploration > Sélecteur de captages / BV | G68: US3.1 ; US3.2 | H68: Restitution – Diffusion | I68: Pilier 4 – Partage & Diffusion | J68: Administrateur expert data | K68: En tant qu'administrateur expert data, je veux calculer les communes intersectant un bassin versant afin d'alimenter la facette Commune. | L68: =SUMIF('Besoins testables'!$D:$D,$A68,'Besoins testables'!$O:$O) -> 0
A69: EPIC 6 – Visualisation | B69: US6.19 | C69: Mettre en évidence le croisement captages ↔ BV sur la carte | D69: True | E69: Front-end | F69: Cartographie & exploration > Cartographie | G69: US3.1 ; US3.2 | H69: Restitution – Diffusion | I69: Pilier 4 – Partage & Diffusion | J69: Administrateur expert data | K69: En tant qu'administrateur expert data, je veux mettre en évidence le croisement captages et bassins versants afin de comprendre leurs liens. | L69: =SUMIF('Besoins testables'!$D:$D,$A69,'Besoins testables'!$O:$O) -> 0
A70: EPIC 6 – Visualisation | B70: US6.20 | C70: Choisir le fond de carte (Carto / Satellite / Terrain) via un sélecteur posé sur la carte | D70: True | E70: Front-end | F70: Cartographie & exploration > Cartographie | H70: Restitution – Diffusion | I70: Pilier 4 – Partage & Diffusion | J70: Intéressé public | K70: En tant qu'intéressé public, je veux choisir le fond de carte afin d'adapter ma lecture au contexte. | L70: =SUMIF('Besoins testables'!$D:$D,$A70,'Besoins testables'!$O:$O) -> 0
A71: EPIC 6 – Visualisation | B71: US6.21 | C71: Afficher / masquer chaque couche (BV, captages, périmètres, zones à risque) depuis une section « Couches » du volet gauche | D71: True | E71: Front-end | F71: Cartographie & exploration > Cartographie | H71: Restitution – Diffusion | I71: Pilier 4 – Partage & Diffusion | J71: Expert métier eau potable | K71: En tant qu'administrateur expert data, je veux afficher ou masquer chaque couche afin de personnaliser ce qui est visible. | L71: [object Object]
A72: EPIC 6 – Visualisation | B72: US6.22 | C72: Rechercher un indicateur dans un dropdown groupé Famille → Thème → Groupe | D72: True | E72: Front-end | F72: Cartographie & exploration > Catalogue d'indicateurs | H72: Restitution – Diffusion | I72: Pilier 4 – Partage & Diffusion | J72: Intéressé public | K72: En tant qu'intéressé public, je veux rechercher un indicateur par famille, thème et groupe afin de le retrouver rapidement. | L72: =SUMIF('Besoins testables'!$D:$D,$A72,'Besoins testables'!$O:$O) -> 0
A73: EPIC 6 – Visualisation | B73: US6.23 | C73: Consulter la fiche métadonnées depuis la vignette de l'indicateur (pas depuis les graphiques) | D73: True | E73: Front-end | F73: Cartographie & exploration > Catalogue d'indicateurs | H73: Restitution – Diffusion | I73: Pilier 4 – Partage & Diffusion | J73: Administrateur expert data | K73: En tant qu'administrateur expert data, je veux consulter la fiche métadonnées d'un indicateur afin d'en vérifier la définition. | L73: =SUMIF('Besoins testables'!$D:$D,$A73,'Besoins testables'!$O:$O) -> 0
A74: EPIC 6 – Visualisation | B74: US6.24 | C74: Basculer chaque graphique entre les vues graphique / Temporel / Changements / H3 | D74: True | E74: Front-end | F74: Cartographie & exploration > Visualisation & dataviz | H74: Restitution – Diffusion | I74: Pilier 4 – Partage & Diffusion | J74: Expert métier eau potable | K74: En tant qu'expert métier eau potable, je veux basculer entre les vues graphiques afin d'analyser la répartition spatiale et l'évolution temporelle. | L74: =SUMIF('Besoins testables'!$D:$D,$A74,'Besoins testables'!$O:$O) -> 0
A75: EPIC 6 – Visualisation | B75: US6.25 | C75: Voir toute la liste des indicateurs (38) regroupée Famille → Thème → Groupe | D75: True | E75: Front-end | F75: Cartographie & exploration > Catalogue d'indicateurs | H75: Restitution – Diffusion | I75: Pilier 4 – Partage & Diffusion | J75: Intéressé public | K75: En tant qu'intéressé public, je veux voir toute la liste des indicateurs afin de connaître ce qui est disponible. | L75: =SUMIF('Besoins testables'!$D:$D,$A75,'Besoins testables'!$O:$O) -> 0
A76: EPIC 6 – Visualisation | B76: US6.26 | C76: Présélectionner les indicateurs du volet droit par famille (tabs), thèmes (pills) et groupe (dropdown) | D76: True | E76: Front-end | F76: Cartographie & exploration > Catalogue d'indicateurs | H76: Restitution – Diffusion | I76: Pilier 4 – Partage & Diffusion | J76: Administrateur expert data | K76: En tant qu'administrateur expert data, je veux présélectionner les indicateurs par famille afin d'orienter l'usage du volet droit. | L76: =SUMIF('Besoins testables'!$D:$D,$A76,'Besoins testables'!$O:$O) -> 0
A77: EPIC 8 – Export | B77: US8.1 | C77: Export CSV | D77: True | E77: Front-end | F77: Export & diffusion | H77: Restitution – Diffusion | I77: Pilier 4 – Partage & Diffusion | J77: Administrateur expert data | K77: En tant qu'administrateur expert data, je veux exporter les données en CSV afin de les réutiliser dans d'autres traitements. | L77: =SUMIF('Besoins testables'!$D:$D,$A77,'Besoins testables'!$O:$O) -> 0
A78: EPIC 8 – Export | B78: US8.2 | C78: Export SIG | D78: False | E78: Front-end | F78: Export & diffusion | H78: Restitution – Diffusion | I78: Pilier 4 – Partage & Diffusion | J78: Administrateur expert data | K78: En tant qu'administrateur expert data, je veux exporter au format SIG afin de réutiliser les données dans un logiciel cartographique.
A79: EPIC 8 – Export | B79: US8.3 | C79: Rapport PDF | D79: False | E79: Front-end | F79: Export & diffusion | G79: US6.7 | H79: Restitution – Diffusion | I79: Pilier 4 – Partage & Diffusion | J79: Décideur métier | K79: En tant que décideur métier, je veux générer un rapport PDF afin de présenter les résultats au conseil municipal et formaliser la prise de décision.
A80: EPIC 8 – Export | B80: US8.4 | C80: Partage lien | D80: False | E80: Front-end | F80: Export & diffusion | H80: Restitution – Diffusion | I80: Pilier 4 – Partage & Diffusion | J80: Administrateur expert data | K80: En tant qu'administrateur expert data, je veux partager un lien afin de transmettre une vue des données à un collaborateur.
A81: EPIC 8 – Export | B81: US8.5 | C81: API | D81: False | E81: Backend | F81: Export & diffusion | H81: Restitution – Diffusion | I81: Pilier 4 – Partage & Diffusion | J81: Administrateur expert data | K81: En tant qu'administrateur expert data, je veux accéder aux données via une API afin de les réutiliser dans d'autres systèmes.
A82: EPIC 8 – Export | B82: US8.6 | C82: Export vue simple | D82: True | E82: Front-end | F82: Export & diffusion | H82: Restitution – Diffusion | I82: Pilier 4 – Partage & Diffusion | J82: Administrateur expert data | K82: En tant qu'administrateur expert data, je veux exporter une vue simple afin de partager un état des données. | L82: =SUMIF('Besoins testables'!$D:$D,$A82,'Besoins testables'!$O:$O) -> 0
A83: EPIC 9 – Utilisateurs | B83: US9.1 | C83: Créer compte | D83: False | E83: Front-end | F83: Administration & profils | G83: US9.2 | H83: Gouvernance | I83: Transverse (socle) | J83: Administrateur plateforme | K83: En tant qu'administrateur plateforme, je veux créer des comptes utilisateurs afin de permettre à chaque usager d'accéder à la plateforme.
A84: EPIC 9 – Utilisateurs | B84: US9.2 | C84: Authentification | D84: True | E84: Front-end | F84: Administration & profils | H84: Gouvernance | I84: Transverse (socle) | J84: Administrateur plateforme | K84: En tant qu'administrateur plateforme, je veux mettre en place l'authentification des utilisateurs afin de sécuriser l'accès à la plateforme. | L84: =SUMIF('Besoins testables'!$D:$D,$A84,'Besoins testables'!$O:$O) -> 0
A85: EPIC 9 – Utilisateurs | B85: US9.3 | C85: Rôles simples | D85: True | E85: Front-end | F85: Administration & profils | G85: US9.2 | H85: Gouvernance | I85: Transverse (socle) | J85: Administrateur plateforme | K85: En tant qu'administrateur plateforme, je veux définir des rôles simples afin d'attribuer des droits adaptés à chaque profil. | L85: =SUMIF('Besoins testables'!$D:$D,$A85,'Besoins testables'!$O:$O) -> 0
A86: EPIC 9 – Utilisateurs | B86: US9.4 | C86: Restreindre accès fin | D86: False | E86: Front-end | F86: Administration & profils | G86: US9.3 ; US8.4 ; US8.5 | H86: Gouvernance | I86: Transverse (socle) | J86: Administrateur plateforme | K86: En tant qu'administrateur plateforme, je veux restreindre finement l'accès aux données et aux fonctionnalités afin de limiter la consultation aux seuls droits autorisés.
A87: EPIC 9 – Utilisateurs | B87: US9.5 | C87: Adapter interface | D87: False | E87: Front-end | F87: Administration & profils | G87: US9.2 ; US9.3 | H87: Gouvernance | I87: Transverse (socle) | J87: Administrateur plateforme | K87: En tant qu'administrateur plateforme, je veux adapter l'interface selon le profil de l'utilisateur afin d'afficher les fonctionnalités pertinentes pour chacun.
A88: EPIC 9 – Utilisateurs | B88: US9.6 | C88: Suivre connexions | D88: False | E88: Backend | F88: Administration & profils | G88: US9.2 | H88: Gouvernance | I88: Transverse (socle) | J88: Administrateur plateforme | K88: En tant qu'administrateur plateforme, je veux suivre les connexions des utilisateurs afin de surveiller l'utilisation de la plateforme.
A89: EPIC 10 – Traçabilité | B89: US10.1 | C89: Tracer imports | D89: True | E89: Backend | F89: Suivi qualité & traçabilité | H89: Gouvernance | I89: Transverse (socle) | J89: Administrateur expert data | K89: En tant qu'administrateur expert data, je veux tracer les imports afin de savoir quelles données ont été chargées. | L89: =SUMIF('Besoins testables'!$D:$D,$A89,'Besoins testables'!$O:$O) -> 0
A90: EPIC 10 – Traçabilité | B90: US10.2 | C90: Tracer calculs | D90: True | E90: Backend | F90: Suivi qualité & traçabilité | G90: US4.1 | H90: Gouvernance | I90: Transverse (socle) | J90: Administrateur expert data | K90: En tant qu'administrateur expert data, je veux tracer les calculs afin de reconstituer leur exécution. | L90: =SUMIF('Besoins testables'!$D:$D,$A90,'Besoins testables'!$O:$O) -> 0
A91: EPIC 10 – Traçabilité | B91: US10.3 | C91: Journal actions | D91: False | E91: Front-end | F91: Suivi qualité & traçabilité | H91: Gouvernance | I91: Transverse (socle) | J91: Administrateur plateforme | K91: En tant qu'administrateur plateforme, je veux consulter le journal des actions afin de tracer les opérations effectuées sur la plateforme.
A92: EPIC 10 – Traçabilité | B92: US10.4 | C92: Historique modifications | D92: False | E92: Front-end | F92: Suivi qualité & traçabilité | G92: US1.6 | H92: Gouvernance | I92: Transverse (socle) | J92: Administrateur expert data | K92: En tant qu'administrateur expert data, je veux consulter l'historique des modifications afin de suivre les changements.
A93: EPIC 10 – Traçabilité | B93: US10.5 | C93: Reconstituer calcul | D93: False | E93: Backend | F93: Suivi qualité & traçabilité | G93: US1.6 ; US10.2 | H93: Gouvernance | I93: Transverse (socle) | J93: Administrateur expert data | K93: En tant qu'administrateur expert data, je veux reconstituer un calcul afin de vérifier un résultat passé.
A94: EPIC 10 – Traçabilité | B94: US10.6 | C94: Audit usages | D94: False | E94: Backend | F94: Suivi qualité & traçabilité | H94: Gouvernance | I94: Transverse (socle) | J94: Administrateur plateforme | K94: En tant qu'administrateur plateforme, je veux auditer les usages de la plateforme afin de contrôler les accès et de justifier les actions.
A95: EPIC 7 – Aide à la décision | B95: US7.1 | C95: Définir des seuils | D95: False | E95: Front-end | F95: Suivi & veille | H95: Exploitation | I95: Pilier 2 – Diagnostic & Analyse multicritère (+ Pilier 3) | J95: Expert métier eau potable | K95: En tant qu'expert métier eau potable, je veux définir des seuils d'alerte afin de qualifier les valeurs des indicateurs et être averti des situations critiques.
A96: EPIC 7 – Aide à la décision | B96: US7.2 | C96: Détecter dépassement | D96: False | E96: Front-end | F96: Suivi & veille | G96: US7.1 | H96: Exploitation | I96: Pilier 2 – Diagnostic & Analyse multicritère (+ Pilier 3) | J96: Décideur métier | K96: En tant qu'expert métier eau potable, je veux détecter les dépassements de seuil afin d'anticiper les périodes de tension sur la ressource.
A97: EPIC 7 – Aide à la décision | B97: US7.3 | C97: Identifier tendances | D97: True | E97: Front-end | F97: Suivi & veille | H97: Exploitation | I97: Pilier 2 – Diagnostic & Analyse multicritère (+ Pilier 3) | J97: Expert métier eau potable | K97: En tant que décideur métier, je veux identifier des tendances sur les indicateurs afin de détecter les évolutions préoccupantes de la ressource. | L97: =SUMIF('Besoins testables'!$D:$D,$A97,'Besoins testables'!$O:$O) -> 0
A98: EPIC 7 – Aide à la décision | B98: US7.4 | C98: Détecter et alerter sur un changement significatif | D98: False | E98: Front-end | F98: Suivi & veille | G98: US7.1 ; US7.3 | H98: Exploitation | I98: Pilier 2 – Diagnostic & Analyse multicritère (+ Pilier 3) | J98: Expert métier eau potable | K98: En tant qu'expert métier eau potable, je veux être alerté lors de la détection d'un changement significatif sur un indicateur ou un territoire afin de déclencher une analyse ou une action en temps opportun. | L98: =SUMIF('Besoins testables'!$D:$D,$A98,'Besoins testables'!$O:$O) -> 0
A99: EPIC 7 – Aide à la décision | B99: US7.5 | C99: Prioriser territoires | D99: False | E99: Front-end | F99: Suivi & veille | G99: US5.1 ; US5.2 | H99: Exploitation | I99: Pilier 2 – Diagnostic & Analyse multicritère (+ Pilier 3) | J99: Expert métier eau potable | K99: En tant qu'expert métier eau potable, je veux prioriser les territoires selon leur score de criticité afin de concentrer les actions sur les zones les plus sensibles.
A100: EPIC 7 – Aide à la décision | B100: US7.6 | C100: Aide à interprétation avancée | D100: False | E100: Front-end | F100: Suivi & veille | H100: Exploitation | I100: Pilier 2 – Diagnostic & Analyse multicritère (+ Pilier 3) | J100: Expert métier eau potable | K100: En tant qu'expert métier eau potable, je veux utiliser l'aide à l'interprétation avancée.

Sheet Besoins testables
A1: Identifiant test | B1: Libellé scénario | C1: EPIC | D1: ID User Story | E1: Libellé User Story | F1: MVP | G1: Front_or_Back | H1: Module | I1: Dépend de (Parent) | J1: Type fonctionnel | K1: Pilier(s) | L1: Profil utilisateur | M1: Phrase méthode agile | N1: Scénario testable (complet) | O1: Point d'effort prestataire (1er niveau)
A2: US1.1-SC01 | B2: Import d'un fichier CSV conforme | C2: EPIC 1 – Gestion des données | D2: US1.1 | E2: Importer des données via fichier | F2: True | G2: Front-end | H2: Gestion des données & catalogue | J2: Acquisition | K2: Pilier 1 – Connaissance & Caractérisation | L2: Administrateur expert data | M2: En tant qu'administrateur expert data, je veux importer des données via fichier afin que la plateforme dispose de données fiables et homogènes. | N2: Étant donné un administrateur expert data connecté, Quand il importe un fichier CSV conforme au modèle attendu (en-têtes, types, unités), Alors les données sont enregistrées dans la plateforme, Et un message de succès indique le nombre de lignes chargées, Et le jeu de données apparaît dans le catalogue comme donnée source.
A3: US1.1-SC02 | B3: Import de données SIG (Shapefile/GeoJSON) | C3: EPIC 1 – Gestion des données | D3: US1.1 | E3: Importer des données via fichier | F3: True | G3: Front-end | H3: Gestion des données & catalogue | J3: Acquisition | K3: Pilier 1 – Connaissance & Caractérisation | L3: Administrateur expert data | M3: En tant qu'administrateur expert data, je veux importer des données via fichier afin que la plateforme dispose de données fiables et homogènes. | N3: Étant donné un fichier au format SIG (Shapefile, GeoJSON), Quand il est importé, Alors les géométries sont validées et converties dans le système de coordonnées de référence de la plateforme, Et les enregistrements invalides sont rejetés avec leur motif.
A4: US1.1-SC03 | B4: Détection des doublons à l'import | C4: EPIC 1 – Gestion des données | D4: US1.1 | E4: Importer des données via fichier | F4: True | G4: Front-end | H4: Gestion des données & catalogue | J4: Acquisition | K4: Pilier 1 – Connaissance & Caractérisation | L4: Administrateur expert data | M4: En tant qu'administrateur expert data, je veux importer des données via fichier afin que la plateforme dispose de données fiables et homogènes. | N4: Étant donné un fichier contenant des doublons (même identifiant captage et même date), Quand l'import est lancé, Alors les doublons sont détectés et signalés, Et aucun doublon n'est enregistré sans validation explicite de l'administrateur.
A5: US1.1-SC04 | B5: Exécution asynchrone d'un import volumineux | C5: EPIC 1 – Gestion des données | D5: US1.1 | E5: Importer des données via fichier | F5: True | G5: Front-end | H5: Gestion des données & catalogue | J5: Acquisition | K5: Pilier 1 – Connaissance & Caractérisation | L5: Administrateur expert data | M5: En tant qu'administrateur expert data, je veux importer des données via fichier afin que la plateforme dispose de données fiables et homogènes. | N5: Étant donné un import volumineux ou long, Quand l'import est lancé, Alors il s'exécute de manière asynchrone avec un statut visible (en cours / terminé / échec), sans bloquer les autres actions de l'administrateur.
A6: US1.1-SC05 | B6: Refus d'un fichier non conforme | C6: EPIC 1 – Gestion des données | D6: US1.1 | E6: Importer des données via fichier | F6: True | G6: Front-end | H6: Gestion des données & catalogue | J6: Acquisition | K6: Pilier 1 – Connaissance & Caractérisation | L6: Administrateur expert data | M6: En tant qu'administrateur expert data, je veux importer des données via fichier afin que la plateforme dispose de données fiables et homogènes. | N6: Étant donné un fichier non conforme (extension non supportée, colonnes obligatoires manquantes), Quand l'administrateur tente l'import, Alors l'import est refusée et un message d'erreur explicite liste les anomalies détectées.
A7: US1.3-SC01 | B7: Planification d'imports automatiques | C7: EPIC 1 – Gestion des données | D7: US1.3 | E7: Planifier des imports simples | F7: True | G7: Backend | H7: Gestion des données & catalogue | I7: US1.1 | J7: Acquisition | K7: Pilier 1 – Connaissance & Caractérisation | L7: Administrateur expert data | M7: En tant qu'administrateur expert data, je veux planifier des imports simples afin que les données soient actualisées automatiquement. | N7: Étant donné une source de données fichier, Quand l'administrateur définit une planification (fréquence journalière, hebdomadaire, mensuelle, heure d'exécution), Alors l'import est exécuté automatiquement à l'échéance prévue, Et chaque exécution est tracée (date, heure, source, résultat, volumétrie). - Quand un import planifié échoue, Alors son statut passe à « échec », l'événement est journalisé avec le motif, Et les exécutions suivantes restent programmées. - Quand la planification est modifiée ou supprimée, Alors seules les nouvelles exécutions respectent la configuration courante, les exécutions déjà tracées restant inchangées. - Quand deux imports planifiés se chevauchent, Alors le système les sérialise ou refuse le chevauchement sans perte de données.
A8: US1.3-SC02 | B8: Échec d'un import planifié sans source | C8: EPIC 1 – Gestion des données | D8: US1.3 | E8: Planifier des imports simples | F8: True | G8: Backend | H8: Gestion des données & catalogue | I8: US1.1 | J8: Acquisition | K8: Pilier 1 – Connaissance & Caractérisation | L8: Administrateur expert data | M8: En tant qu'administrateur expert data, je veux planifier des imports simples afin que les données soient actualisées automatiquement. | N8: Étant donné un import planifié sans fichier source disponible à l'échéance, Alors l'exécution est signalée en échec avec un motif explicite, Et aucune donnée partielle ou vide n'est enregistrée.
A9: US1.4-SC01 | B9: Normalisation de données hétérogènes | C9: EPIC 1 – Gestion des données | D9: US1.4 | E9: Normaliser les données | F9: True | G9: Backend | H9: Gestion des données & catalogue | I9: US1.1 | J9: Structuration | K9: Pilier 1 – Connaissance & Caractérisation | L9: Administrateur expert data | M9: En tant qu'administrateur expert data, je veux normaliser les données afin qu'elles soient homogènes et comparables. | N9: Étant donné des données brutes hétérogènes (unités, formats de date, nomenclatures), Quand elles sont intégrées, Alors elles sont converties selon les règles de normalisation de la plateforme (unités de référence, dates ISO 8601, identifiants des référentiels), Et chaque transformation est documentée et tracée.
A10: US1.4-SC02 | B10: Rattachement à un objet du référentiel | C10: EPIC 1 – Gestion des données | D10: US1.4 | E10: Normaliser les données | F10: True | G10: Backend | H10: Gestion des données & catalogue | I10: US1.1 | J10: Structuration | K10: Pilier 1 – Connaissance & Caractérisation | L10: Administrateur expert data | M10: En tant qu'administrateur expert data, je veux normaliser les données afin qu'elles soient homogènes et comparables. | N10: Étant donné une valeur référant à un captage ou un BVAEP, Quand la normalisation s'exécute, Alors la valeur est rattachée à l'objet correspondant du référentiel, Et toute valeur non rattachable est signalée en anomalie sans bloquer le reste du jeu.
A11: US1.4-SC03 | B11: Rejet d'une valeur hors plage | C11: EPIC 1 – Gestion des données | D11: US1.4 | E11: Normaliser les données | F11: True | G11: Backend | H11: Gestion des données & catalogue | I11: US1.1 | J11: Structuration | K11: Pilier 1 – Connaissance & Caractérisation | L11: Administrateur expert data | M11: En tant qu'administrateur expert data, je veux normaliser les données afin qu'elles soient homogènes et comparables. | N11: Étant donné une valeur numérique hors plage ou un format inattendu, Quand la normalisation échoue pour cette ligne, Alors la ligne est marquée « non normalisée », Et le reste du jeu est traité sans blocage global. - Quand aucune règle de normalisation n'existe pour une colonne obligatoire, Alors l'import est refusée avec un message renvoyant vers la configuration de la source. - Quand un jeu de données normalisé est réimporté, Alors les mêmes règles produisent les mêmes valeurs (reproductibilité de la normalisation).
A12: US1.5-SC01 | B12: Rapport d'erreurs avec rejet partiel | C12: EPIC 1 – Gestion des données | D12: US1.5 | E12: Gérer les erreurs d'import | F12: True | G12: Front-end | H12: Gestion des données & catalogue | I12: US1.1 | J12: Acquisition | K12: Pilier 1 – Connaissance & Caractérisation | L12: Administrateur expert data | M12: En tant qu'administrateur expert data, je veux gérer les erreurs d'import afin de corriger les données rejetées efficacement. | N12: Étant donné un fichier CSV contenant 3 lignes invalides sur 100, Quand l'import est exécuté, Alors un rapport d'erreurs est généré listant les 3 lignes avec leur motif de rejet, Et les 97 lignes valides sont enregistrées. - Quand l'administrateur ouvre le rapport d'erreurs, Alors il voit pour chaque erreur le numéro de ligne, la valeur en cause et le motif (type, plage, rattachement référentiel, doublon).
A13: US1.5-SC02 | B13: Refus global d'un import invalide | C13: EPIC 1 – Gestion des données | D13: US1.5 | E13: Gérer les erreurs d'import | F13: True | G13: Front-end | H13: Gestion des données & catalogue | I13: US1.1 | J13: Acquisition | K13: Pilier 1 – Connaissance & Caractérisation | L13: Administrateur expert data | M13: En tant qu'administrateur expert data, je veux gérer les erreurs d'import afin de corriger les données rejetées efficacement. | N13: Étant donné un fichier entièrement invalide, Quand aucun enregistrement ne passe les contrôles, Alors l'import est refusée dans sa globalité et aucun enregistrement n'est créé. - Quand un import se termine avec des rejets, Alors un message d'alerte informe l'administrateur du nombre d'enregistrements rejetés, avec un lien vers le rapport d'erreurs.
A14: US1.5-SC03 | B14: Relance d'import après correction | C14: EPIC 1 – Gestion des données | D14: US1.5 | E14: Gérer les erreurs d'import | F14: True | G14: Front-end | H14: Gestion des données & catalogue | I14: US1.1 | J14: Acquisition | K14: Pilier 1 – Connaissance & Caractérisation | L14: Administrateur expert data | M14: En tant qu'administrateur expert data, je veux gérer les erreurs d'import afin de corriger les données rejetées efficacement. | N14: Étant donné un fichier corrigé après un rejet, Quand l'administrateur relance l'import, Alors seules les nouvelles anomalies sont signalées, les lignes précédemment corrigées n'apparaissant plus dans le rapport.
A15: US1.6-SC01 | B15: Création de versions historisées | C15: EPIC 1 – Gestion des données | D15: US1.6 | E15: Historiser les données | F15: True | G15: Backend | H15: Gestion des données & catalogue | I15: US1.1 | J15: Gouvernance | K15: Transverse (socle) | L15: Administrateur expert data | M15: En tant qu'administrateur expert data, je veux historiser les données afin de reconstituer leur évolution dans le temps. | N15: Étant donné un jeu de données déjà importé, Quand un nouvel import met à jour ce jeu, Alors une nouvelle version est créée, Et les versions antérieures sont intégralement conservées et consultables. - Quand une donnée est modifiée ou supprimée, Alors l'historisation conserve l'intégralité des versions antérieures : aucune valeur écrasée n'est perdue.
A16: US1.6-SC02 | B16: Reconstitution d'un état à une date | C16: EPIC 1 – Gestion des données | D16: US1.6 | E16: Historiser les données | F16: True | G16: Backend | H16: Gestion des données & catalogue | I16: US1.1 | J16: Gouvernance | K16: Transverse (socle) | L16: Administrateur expert data | M16: En tant qu'administrateur expert data, je veux historiser les données afin de reconstituer leur évolution dans le temps. | N16: Étant donné une date de référence, Quand l'administrateur interroge l'historique, Alors il peut reconstituer l'état du jeu de données tel qu'il existait à cette date. - Quand une nouvelle version est enregistrée, Alors son horodatage, sa source et le traitement d'origine sont tracés. - Quand une opération de réécriture est demandée, Alors aucune donnée existante n'est écrasée sans création préalable d'une nouvelle version (aucune suppression destructive). ### EPIC 1bis — Catalogage des données
A17: US1bis.1-SC01 | B17: Enregistrement d'un jeu dans le catalogue | C17: EPIC 1bis – Catalogage des données | D17: US1bis.1 | E17: Enregistrer un jeu de données dans le catalogue | F17: True | G17: Front-end | H17: Gestion des données & catalogue | I17: US1.2 | J17: Structuration | K17: Pilier 1 – Connaissance & Caractérisation | L17: Administrateur expert data | M17: En tant qu'administrateur expert data, je veux enregistrer un jeu de données dans le catalogue afin qu'il soit référencé et trouvable. | N17: Étant donné un jeu de données intégré dans la plateforme, Quand l'administrateur l'enregistre dans le catalogue, Alors il reçoit un identifiant unique de catalogue, Et il devient visible et trouvable dans la liste du catalogue. - Quand un jeu de données est enregistré, Alors les champs obligatoires suivants sont renseignés et validés : nom, fournisseur, date de mise à jour, licence ; l'enregistrement est refusé tant qu'ils sont manquants.
A18: US1bis.1-SC02 | B18: Refus d'un identifiant déjà utilisé | C18: EPIC 1bis – Catalogage des données | D18: US1bis.1 | E18: Enregistrer un jeu de données dans le catalogue | F18: True | G18: Front-end | H18: Gestion des données & catalogue | I18: US1.2 | J18: Structuration | K18: Pilier 1 – Connaissance & Caractérisation | L18: Administrateur expert data | M18: En tant qu'administrateur expert data, je veux enregistrer un jeu de données dans le catalogue afin qu'il soit référencé et trouvable. | N18: Étant donné un identifiant de catalogue déjà utilisé, Quand l'administrateur tente d'enregistrer un autre jeu avec cet identifiant, Alors l'enregistrement est refusée et un message explicite s'affiche. - Quand un jeu de données enregistré est mis à jour (nouvel import), Alors la fiche du catalogue reste liée à la version courante du jeu.
... A22: US1bis.2-SC03 | B22: Refus d'une licence non autorisée | C22: EPIC 1bis – Catalogage des données | D22: US1bis.2 | E22: Associer des métadonnées à un jeu de données | F22: True | G22: Front-end | H22: Gestion des données & catalogue | I22: US1bis.1 | J22: Structuration | K22: Pilier 1 – Connaissance & Caractérisation | L22: Administrateur expert data | M22: En tant qu'administrateur expert data, je veux associer des métadonnées à un jeu de données afin d'en documenter l'origine et la structure. | N22: Étant donné une licence non autorisée ou une date de mise à jour future, Quand l'enregistrement est tenté, Alors il est refusé avec un message d'erreur explicite.
A23: US1bis.4-SC01 | B23: Consultation d'une fiche de jeu de données | C23: EPIC 1bis – Catalogage des données | D23: US1bis.4 | E23: Consulter les informations d'un jeu de données | F23: True | G23: Front-end | H23: Gestion des données & catalogue | J23: Structuration | K23: Pilier 1 – Connaissance & Caractérisation | L23: Administrateur expert data | M23: En tant qu'administrateur expert data, je veux consulter les informations d'un jeu de données afin d'en connaître le contenu et la source. | N23: Étant donné un jeu de données du catalogue, Quand l'utilisateur ouvre sa fiche, Alors il voit son nom, son fournisseur, sa date de mise à jour, sa licence, sa couverture spatiale et temporelle, et son type (donnée source ou donnée dérivée). - Quand l'utilisateur consulte la fiche, Alors il voit la structure du jeu (champs, types, unités) et, si disponible, un aperçu du contenu.
A24: US1bis.4-SC02 | B24: Fiche d'un jeu dérivé | C24: EPIC 1bis – Catalogage des données | D24: US1bis.4 | E24: Consulter les informations d'un jeu de données | F24: True | G24: Front-end | H24: Gestion des données & catalogue | J24: Structuration | K24: Pilier 1 – Connaissance & Caractérisation | L24: Administrateur expert data | M24: En tant qu'administrateur expert data, je veux consulter les informations d'un jeu de données afin d'en connaître le contenu et la source. | N24: Étant donné un jeu de données dérivé, Quand sa fiche est consultée, Alors elle affiche les données sources et les traitements dont il provient.
A25: US1bis.4-SC03 | B25: Affichage d'une licence non renseignée | C25: EPIC 1bis – Catalogage des données | D25: US1bis.4 | E25: Consulter les informations d'un jeu de données | F25: True | G25: Front-end | H25: Gestion des données & catalogue | J25: Structuration | K25: Pilier 1 – Connaissance & Caractérisation | L25: Administrateur expert data | M25: En tant qu'administrateur expert data, je veux consulter les informations d'un jeu de données afin d'en connaître le contenu et la source. | N25: Étant donné un jeu de données sans licence renseignée, Quand sa fiche est consultée, Alors la mention « licence non renseignée » est affichée (aucune valeur par défaut trompeuse). - Quand la fiche est consultée depuis le catalogue, Alors l'utilisateur voit les métadonnées de qualité associées (EPIC 2) si elles existent.
A26: US1bis.7-SC01 | B26: Visualisation du graphe de relations | C26: EPIC 1bis – Catalogage des données | D26: US1bis.7 | E26: Visualiser les relations entre indicateur et données sources | F26: True | G26: Front-end | H26: Gestion des données & catalogue | J26: Structuration | K26: Pilier 1 – Connaissance & Caractérisation | L26: Administrateur expert data | M26: En tant qu'administrateur expert data, je veux visualiser les relations entre un indicateur et ses données sources afin d'en comprendre la provenance. | N26: Étant donné un indicateur dérivé, Quand l'utilisateur ouvre sa page de relations, Alors il voit un graphe reliant l'indicateur à ses données sources et aux traitements intermédiaires. - Quand l'utilisateur clique sur un nœud du graphe (jeu de données source, traitement), Alors les métadonnées correspondantes sont affichées.
A27: US1bis.7-SC02 | B27: Précision de la période de calcul | C27: EPIC 1bis – Catalogage des données | D27: US1bis.7 | E27: Visualiser les relations entre indicateur et données sources | F27: True | G27: Front-end | H27: Gestion des données & catalogue | J27: Structuration | K27: Pilier 1 – Connaissance & Caractérisation | L27: Administrateur expert data | M27: En tant qu'administrateur expert data, je veux visualiser les relations entre un indicateur et ses données sources afin d'en comprendre la provenance. | N27: Étant donné un indicateur calculé sur des données historisées, Quand le graphe est affiché, Alors la version ou la période des données utilisées pour le calcul courant est précisée.
A28: US1bis.7-SC03 | B28: Absence de relations tracées | C28: EPIC 1bis – Catalogage des données | D28: US1bis.7 | E28: Visualiser les relations entre indicateur et données sources | F28: True | G28: Front-end | H28: Gestion des données & catalogue | J28: Structuration | K28: Pilier 1 – Connaissance & Caractérisation | L28: Administrateur expert data | M28: En tant qu'administrateur expert data, je veux visualiser les relations entre un indicateur et ses données sources afin d'en comprendre la provenance. | N28: Étant donné un indicateur sans dépendance déclarée, Quand la page est ouverte, Alors un message indique l'absence de relations tracées plutôt qu'un graphe vide. - Quand l'indicateur est recalculé sur de nouvelles données, Alors le graphe reflète les relations de la version de calcul la plus récente.
A29: US1bis.10-SC01 | B29: Alimentation automatique du catalogue | C29: EPIC 1bis – Catalogage des données | D29: US1bis.10 | E29: Alimenter automatiquement le catalogue lors des imports | F29: True | G29: Backend | H29: Gestion des données & catalogue | I29: US1.1 ; US1bis.1 | J29: Acquisition | K29: Pilier 1 – Connaissance & Caractérisation | L29: Administrateur expert data | M29: En tant qu'administrateur expert data, je veux alimenter automatiquement le catalogue lors des imports afin d'éviter les saisies manuelles. | N29: Étant donné un import de fichier réussi, Quand le traitement se termine, Alors une entrée de catalogue est créée ou mise à jour automatiquement, sans saisie manuelle.
A30: US1bis.10-SC02 | B30: Mise à jour sans doublon | C30: EPIC 1bis – Catalogage des données | D30: US1bis.10 | E30: Alimenter automatiquement le catalogue lors des imports | F30: True | G30: Backend | H30: Gestion des données & catalogue | I30: US1.1 ; US1bis.1 | J30: Acquisition | K30: Pilier 1 – Connaissance & Caractérisation | L30: Administrateur expert data | M30: En tant qu'administrateur expert data, je veux alimenter automatiquement le catalogue lors des imports afin d'éviter les saisies manuelles. | N30: Étant donné un jeu de données déjà catalogué, Quand un import le met à jour, Alors sa fiche de catalogue est actualisée (date de mise à jour, version courante) sans création de doublon.
A31: US1bis.10-SC03 | B31: Aucune entrée en cas d'échec | C31: EPIC 1bis – Catalogage des données | D31: US1bis.10 | E31: Alimenter automatiquement le catalogue lors des imports | F31: True | G31: Backend | H31: Gestion des données & catalogue | I31: US1.1 ; US1bis.1 | J31: Acquisition | K31: Pilier 1 – Connaissance & Caractérisation | L31: Administrateur expert data | M31: En tant qu'administrateur expert data, je veux alimenter automatiquement le catalogue lors des imports afin d'éviter les saisies manuelles. | N31: Étant donné un import en échec, Quand le traitement se termine, Alors aucune entrée de catalogue n'est créée, Et l'événement est tracé. - Quand une entrée est créée automatiquement, Alors les métadonnées minimales (nom, fournisseur, date de mise à jour) sont déduites de l'import et marquées « générées automatiquement ».
A32: US1bis.10-SC04 | B32: Échec partiel sans identifiant | C32: EPIC 1bis – Catalogage des données | D32: US1bis.10 | E32: Alimenter automatiquement le catalogue lors des imports | F32: True | G32: Backend | H32: Gestion des données & catalogue | I32: US1.1 ; US1bis.1 | J32: Acquisition | K32: Pilier 1 – Connaissance & Caractérisation | L32: Administrateur expert data | M32: En tant qu'administrateur expert data, je veux alimenter automatiquement le catalogue lors des imports afin d'éviter les saisies manuelles. | N32: Étant donné un import sans identifiant de jeu identifiable, Quand l'alimentation du catalogue est tentée, Alors l'import est signalé en échec partiel avec le motif.
A33: US1bis.12-SC01 | B33: Enregistrement d'un indicateur dérivé | C33: EPIC 1bis – Catalogage des données | D33: US1bis.12 | E33: Enregistrer un indicateur comme donnée dérivée | F33: True | G33: Front-end | H33: Gestion des données & catalogue | I33: US3.5 | J33: Structuration | K33: Pilier 1 – Connaissance & Caractérisation | L33: Administrateur expert data | M33: En tant qu'administrateur expert data, je veux enregistrer un indicateur comme donnée dérivée afin qu'il soit identifié comme tel dans le catalogue. | N33: Étant donné un indicateur défini dans le référentiel (US3.5), Quand il est enregistré dans le catalogue, Alors il apparaît avec le type « donnée dérivée », distinct des données sources. - Quand la fiche de l'indicateur est consultée, Alors elle indique qu'il s'agit d'une donnée dérivée et renvoie vers sa définition et sa méthode de calcul.
A34: US1bis.12-SC02 | B34: Refus sans donnée source | C34: EPIC 1bis – Catalogage des données | D34: US1bis.12 | E34: Enregistrer un indicateur comme donnée dérivée | F34: True | G34: Front-end | H34: Gestion des données & catalogue | I34: US3.5 | J34: Structuration | K34: Pilier 1 – Connaissance & Caractérisation | L34: Administrateur expert data | M34: En tant qu'administrateur expert data, je veux enregistrer un indicateur comme donnée dérivée afin qu'il soit identifié comme tel dans le catalogue. | N34: Étant donné un enregistrement sans lien vers une donnée source ou un traitement, Quand il est tenté, Alors il est refusé : tout indicateur dérivé référence au moins une donnée source ou un traitement.
A35: US1bis.12-SC03 | B35: Refus d'un indicateur non référencé | C35: EPIC 1bis – Catalogage des données | D35: US1bis.12 | E35: Enregistrer un indicateur comme donnée dérivée | F35: True | G35: Front-end | H35: Gestion des données & catalogue | I35: US3.5 | J35: Structuration | K35: Pilier 1 – Connaissance & Caractérisation | L35: Administrateur expert data | M35: En tant qu'administrateur expert data, je veux enregistrer un indicateur comme donnée dérivée afin qu'il soit identifié comme tel dans le catalogue. | N35: Étant donné un indicateur non défini dans le référentiel, Quand l'administrateur tente de l'enregistrer, Alors l'enregistrement est refusé avec un message renvoyant vers la définition de l'indicateur (US3.5). - Quand un indicateur dérivé est recalculé, Alors la version cataloguée est mise à jour, Et la traçabilité du calcul (date, version de la méthode, données utilisées) est conservée. ### EPIC 2 — Qualité des données
A36: US2.1-SC01 | B36: Détection de valeurs aberrantes | C36: EPIC 2 – Qualité des données | D36: US2.1 | E36: Détecter des valeurs aberrantes | F36: True | G36: Backend | H36: Suivi qualité & traçabilité | J36: Qualification | K36: Pilier 1 – Connaissance & Caractérisation (fondement) | L36: Administrateur expert data | M36: En tant qu'administrateur expert data, je veux détecter des valeurs aberrantes afin d'identifier les données à corriger. | N36: Étant donné un jeu de données avec des règles de contrôle définies (bornes min/max, plages attendues), Quand une valeur sort de la plage attendue, Alors l'anomalie est détectée et enregistrée avec le jeu de données, la ligne, la valeur et la règle violée. - Quand la détection est exécutée, Alors un rapport liste les valeurs aberrantes avec leur motif, sans modifier les données d'origine.
A37: US2.1-SC02 | B37: Exclusion d'une valeur erronée | C37: EPIC 2 – Qualité des données | D37: US2.1 | E37: Détecter des valeurs aberrantes | F37: True | G37: Backend | H37: Suivi qualité & traçabilité | J37: Qualification | K37: Pilier 1 – Connaissance & Caractérisation (fondement) | L37: Administrateur expert data | M37: En tant qu'administrateur expert data, je veux détecter des valeurs aberrantes afin d'identifier les données à corriger. | N37: Étant donné une valeur aberrante détectée et validée comme erronée par l'administrateur, Alors elle est exclue des traitements ou marquée non fiable, tout en restant disponible dans l'historique.
A38: US2.1-SC03 | B38: Blanchiment d'un faux positif | C38: EPIC 2 – Qualité des données | D38: US2.1 | E38: Détecter des valeurs aberrantes | F38: True | G38: Backend | H38: Suivi qualité & traçabilité | J38: Qualification | K38: Pilier 1 – Connaissance & Caractérisation (fondement) | L38: Administrateur expert data | M38: En tant qu'administrateur expert data, je veux détecter des valeurs aberrantes afin d'identifier les données à corriger. | N38: Étant donné une valeur signalée à tort (faux positif), Quand l'administrateur la blanchit, Alors le motif du blanchiment est documenté et tracé.
A39: US2.1-SC04 | B39: Jeu non contrôlé | C39: EPIC 2 – Qualité des données | D39: US2.1 | E39: Détecter des valeurs aberrantes | F39: True | G39: Backend | H39: Suivi qualité & traçabilité | J39: Qualification | K39: Pilier 1 – Connaissance & Caractérisation (fondement) | L39: Administrateur expert data | M39: En tant qu'administrateur expert data, je veux détecter des valeurs aberrantes afin d'identifier les données à corriger. | N39: Étant donné un jeu sans règles de détection configurées, Quand le contrôle est exécuté, Alors aucune valeur aberrante n'est signalée et le jeu est qualifié « non contrôlé ».
A40: US2.4-SC01 | B40: Calcul du taux de complétude | C40: EPIC 2 – Qualité des données | D40: US2.4 | E40: Calculer un taux de complétude | F40: True | G40: Backend | H40: Suivi qualité & traçabilité | J40: Qualification | K40: Pilier 1 – Connaissance & Caractérisation (fondement) | L40: Administrateur expert data | M40: En tant qu'administrateur expert data, je veux calculer un taux de complétude afin de mesurer la couverture des données. | N40: Étant donné un jeu de données avec des champs obligatoires définis, Quand le taux de complétude est calculé, Alors il correspond au pourcentage de valeurs renseignées sur les valeurs attendues, par champ et par jeu, Et le résultat est stocké comme métadonnée de qualité. - Quand un taux est calculé, Alors la période et la version du jeu de données utilisées pour le calcul sont précisées.
A41: US2.4-SC02 | B41: Marquage sous le seuil de complétude | C41: EPIC 2 – Qualité des données | D41: US2.4 | E41: Calculer un taux de complétude | F41: True | G41: Backend | H41: Suivi qualité & traçabilité | J41: Qualification | K41: Pilier 1 – Connaissance & Caractérisation (fondement) | L41: Administrateur expert data | M41: En tant qu'administrateur expert data, je veux calculer un taux de complétude afin de mesurer la couverture des données. | N41: Étant donné un seuil de complétude configuré (par défaut 95 %), Quand le taux calculé est inférieur au seuil, Alors le jeu est marqué comme sous le seuil, Et l'information est reportée sur sa fiche qualité. - Quand un jeu est mis à jour (nouvel import, corrections), Alors le taux est recalculé sur la dernière version, sans perte des taux historiques. - Quand le taux de complétude d'un jeu sert au calcul d'un indicateur (EPIC 4), Alors il est exploitable de façon automatisée (filtrage ou marquage du résultat).
A42: US2.5-SC01 | B42: Attribution d'une classe de fiabilité | C42: EPIC 2 – Qualité des données | D42: US2.5 | E42: Qualifier la fiabilité | F42: True | G42: Backend | H42: Suivi qualité & traçabilité | J42: Qualification | K42: Pilier 1 – Connaissance & Caractérisation (fondement) | L42: Administrateur expert data | M42: En tant qu'administrateur expert data, je veux qualifier la fiabilité afin d'évaluer la confiance à accorder aux données. | N42: Étant donné les critères de fiabilité définis (source, méthode de production, complétude, fréquence de mise à jour), Quand la fiabilité d'un jeu de données est évaluée, Alors une classe de fiabilité (élevée, moyenne, faible) lui est attribuée selon des règles documentées. - Quand une classe de fiabilité est attribuée, Alors la règle et les critères utilisés sont tracés.
A43: US2.5-SC02 | B43: Réévaluation de la fiabilité | C43: EPIC 2 – Qualité des données | D43: US2.5 | E43: Qualifier la fiabilité | F43: True | G43: Backend | H43: Suivi qualité & traçabilité | J43: Qualification | K43: Pilier 1 – Connaissance & Caractérisation (fondement) | L43: Administrateur expert data | M43: En tant qu'administrateur expert data, je veux qualifier la fiabilité afin d'évaluer la confiance à accorder aux données. | N43: Étant donné un jeu dont la qualité évolue (nouvel import, corrections), Quand la fiabilité est réévaluée, Alors la classe est recalculée, Et l'évolution est conservée dans l'historique des indicateurs de qualité.
A44: US2.5-SC03 | B44: Fiabilité non évaluée | C44: EPIC 2 – Qualité des données | D44: US2.5 | E44: Qualifier la fiabilité | F44: True | G44: Backend | H44: Suivi qualité & traçabilité | J44: Qualification | K44: Pilier 1 – Connaissance & Caractérisation (fondement) | L44: Administrateur expert data | M44: En tant qu'administrateur expert data, je veux qualifier la fiabilité afin d'évaluer la confiance à accorder aux données. | N44: Étant donné un jeu sans métadonnées de qualité renseignées, Quand l'évaluation est demandée, Alors aucune classe n'est attribuée : le jeu est qualifié « fiabilité non évaluée » (pas de note par défaut trompeuse). - Quand une classe de fiabilité est disponible, Alors elle est exploitable par les traitements ultérieurs (filtrage, affichage différencié).
A45: US2.6-SC01 | B45: Association de métadonnées de qualité | C45: EPIC 2 – Qualité des données | D45: US2.6 | E45: Associer des métadonnées | F45: True | G45: Front-end | H45: Suivi qualité & traçabilité | J45: Qualification | K45: Pilier 1 – Connaissance & Caractérisation (fondement) | L45: Administrateur expert data | M45: En tant qu'administrateur expert data, je veux associer des métadonnées de qualité afin de documenter les contrôles effectués. | N45: Étant donné un jeu de données contrôlé, Quand l'administrateur associe des métadonnées de qualité, Alors il renseigne : date du dernier contrôle, règles appliquées, résultats (anomalies, taux de complétude, fiabilité) et statut de validation. - Quand des métadonnées de qualité sont enregistrées, Alors elles sont visibles sur la fiche qualité du jeu de données.
A46: US2.6-SC02 | B46: Alimentation automatique des métadonnées | C46: EPIC 2 – Qualité des données | D46: US2.6 | E46: Associer des métadonnées | F46: True | G46: Front-end | H46: Suivi qualité & traçabilité | J46: Qualification | K46: Pilier 1 – Connaissance & Caractérisation (fondement) | L46: Administrateur expert data | M46: En tant qu'administrateur expert data, je veux associer des métadonnées de qualité afin de documenter les contrôles effectués. | N46: Étant donné un contrôle automatique, Quand il s'exécute, Alors ses résultats alimentent les métadonnées de qualité sans saisie manuelle, Et l'horodatage du contrôle est tracé.
A47: US2.6-SC03 | B47: Refus d'ajout sur jeu non intégré | C47: EPIC 2 – Qualité des données | D47: US2.6 | E47: Associer des métadonnées | F47: True | G47: Front-end | H47: Suivi qualité & traçabilité | J47: Qualification | K47: Pilier 1 – Connaissance & Caractérisation (fondement) | L47: Administrateur expert data | M47: En tant qu'administrateur expert data, je veux associer des métadonnées de qualité afin de documenter les contrôles effectués. | N47: Étant donné un jeu de données non intégré dans la plateforme, Quand l'administrateur tente d'ajouter des métadonnées de qualité, Alors l'opération est refusée avec un message explicite. - Quand l'administrateur consulte la fiche qualité, Alors il voit un résumé : date du dernier contrôle, classe de fiabilité, taux de complétude, nombre d'anomalies ouvertes. ### EPIC 3 — Référentiels
... A59: US3.5-SC03 | B59: Refus d'un indicateur en double | C59: EPIC 3 – Référentiels | D59: US3.5 | E59: Définir un indicateur | F59: True | G59: Front-end | H59: Administration & profils | J59: Structuration | K59: Pilier 1 – Connaissance & Caractérisation | L59: Administrateur expert data | M59: En tant qu'administrateur expert data, je veux définir un indicateur afin de le rendre calculable et affichable. | N59: Étant donné un indicateur déjà défini sous le même nom ou le même identifiant, Quand la définition est tentée, Alors elle est refusée avec un message explicite. ### EPIC 4 — Calcul d'indicateurs
A60: US4.1-SC01 | B60: Calcul d'indicateurs simples | C60: EPIC 4 – Calcul d'indicateurs | D60: US4.1 | E60: Calculer des indicateurs simples | F60: True | G60: Backend | H60: Gestion des données & catalogue | I60: US3.5 ; US4.7 ; US1bis.12 | J60: Exploitation | K60: Pilier 2 – Diagnostic & Analyse multicritère (+ Pilier 3) | L60: Administrateur expert data | M60: En tant qu'administrateur expert data, je veux calculer des indicateurs simples afin de produire des valeurs fiables. | N60: Étant donné un indicateur défini (US3.5) et ses données sources cataloguées et qualifiées, Quand le calcul est exécuté, Alors les valeurs produites respectent la méthode définie (moyenne, médiane, somme, fréquence, occurrence), Et le résultat est stocké avec la date de calcul, la version de la définition et les versions des données utilisées.
A61: US4.1-SC02 | B61: Marquage « non fiable » sur données manquantes | C61: EPIC 4 – Calcul d'indicateurs | D61: US4.1 | E61: Calculer des indicateurs simples | F61: True | G61: Backend | H61: Gestion des données & catalogue | I61: US3.5 ; US4.7 ; US1bis.12 | J61: Exploitation | K61: Pilier 2 – Diagnostic & Analyse multicritère (+ Pilier 3) | L61: Administrateur expert data | M61: En tant qu'administrateur expert data, je veux calculer des indicateurs simples afin de produire des valeurs fiables. | N61: Étant donné un calcul reposant sur des données manquantes ou sous le seuil de complétude, Quand le résultat est produit, Alors il est marqué « non fiable » ou non calculé selon les règles de l'indicateur.
A62: US4.1-SC03 | B62: Traçage d'un échec de calcul | C62: EPIC 4 – Calcul d'indicateurs | D62: US4.1 | E62: Calculer des indicateurs simples | F62: True | G62: Backend | H62: Gestion des données & catalogue | I62: US3.5 ; US4.7 ; US1bis.12 | J62: Exploitation | K62: Pilier 2 – Diagnostic & Analyse multicritère (+ Pilier 3) | L62: Administrateur expert data | M62: En tant qu'administrateur expert data, je veux calculer des indicateurs simples afin de produire des valeurs fiables. | N62: Étant donné un calcul en échec, Quand il se termine, Alors aucune valeur n'est publiée, Et l'échec est tracé avec son motif. - Quand le calcul est relancé après correction des données, Alors le résultat est recalculé et la nouvelle exécution est tracée (reproductibilité).
A63: US4.1-SC04 | B63: Refus sans méthode complète | C63: EPIC 4 – Calcul d'indicateurs | D63: US4.1 | E63: Calculer des indicateurs simples | F63: True | G63: Backend | H63: Gestion des données & catalogue | I63: US3.5 ; US4.7 ; US1bis.12 | J63: Exploitation | K63: Pilier 2 – Diagnostic & Analyse multicritère (+ Pilier 3) | L63: Administrateur expert data | M63: En tant qu'administrateur expert data, je veux calculer des indicateurs simples afin de produire des valeurs fiables. | N63: Étant donné un indicateur sans méthode complète ou sans données sources, Quand le calcul est demandé, Alors il est refusé avec un message explicite.
A64: US4.2-SC01 | B64: Agrégation à l'échelle bassin versant | C64: EPIC 4 – Calcul d'indicateurs | D64: US4.2 | E64: Agréger à l'échelle BV | F64: True | G64: Backend | H64: Gestion des données & catalogue | I64: US3.1 ; US4.1 | J64: Exploitation | K64: Pilier 2 – Diagnostic & Analyse multicritère (+ Pilier 3) | L64: Administrateur expert data | M64: En tant qu'administrateur expert data, je veux agréger à l'échelle du bassin versant afin de disposer de valeurs synthétiques. | N64: Étant donné des valeurs à l'échelle captage ou maille H3, Quand l'agrégation à l'échelle du BVAEP est exécutée, Alors une valeur synthétique est produite pour chaque bassin versant selon la règle d'agrégation définie (somme, moyenne, moyenne pondérée), Et la règle utilisée est tracée. - Quand le résultat d'agrégation est produit, Alors il est accompagné de la liste des captages pris en compte et du taux de complétude associé.
A65: US4.2-SC02 | B65: Exclusion d'un captage non rattaché | C65: EPIC 4 – Calcul d'indicateurs | D65: US4.2 | E65: Agréger à l'échelle BV | F65: True | G65: Backend | H65: Gestion des données & catalogue | I65: US3.1 ; US4.1 | J65: Exploitation | K65: Pilier 2 – Diagnostic & Analyse multicritère (+ Pilier 3) | L65: Administrateur expert data | M65: En tant qu'administrateur expert data, je veux agréger à l'échelle du bassin versant afin de disposer de valeurs synthétiques. | N65: Étant donné un captage non rattaché à un BVAEP, Quand l'agrégation est exécutée, Alors il est exclu du calcul et signalé dans les anomalies.
A66: US4.2-SC03 | B66: Cohérence historique du périmètre | C66: EPIC 4 – Calcul d'indicateurs | D66: US4.2 | E66: Agréger à l'échelle BV | F66: True | G66: Backend | H66: Gestion des données & catalogue | I66: US3.1 ; US4.1 | J66: Exploitation | K66: Pilier 2 – Diagnostic & Analyse multicritère (+ Pilier 3) | L66: Administrateur expert data | M66: En tant qu'administrateur expert data, je veux agréger à l'échelle du bassin versant afin de disposer de valeurs synthétiques. | N66: Étant donné une évolution du périmètre d'un BVAEP, Quand l'agrégation est exécutée sur une période passée, Alors elle utilise la version du périmètre applicable à cette période (cohérence historique).
A67: US4.2-SC04 | B67: Refus sans règle d'agrégation | C67: EPIC 4 – Calcul d'indicateurs | D67: US4.2 | E67: Agréger à l'échelle BV | F67: True | G67: Backend | H67: Gestion des données & catalogue | I67: US3.1 ; US4.1 | J67: Exploitation | K67: Pilier 2 – Diagnostic & Analyse multicritère (+ Pilier 3) | L67: Administrateur expert data | M67: En tant qu'administrateur expert data, je veux agréger à l'échelle du bassin versant afin de disposer de valeurs synthétiques. | N67: Étant donné un indicateur sans règle d'agrégation spatiale définie, Quand l'agrégation à l'échelle BV est demandée, Alors elle est refusée avec un message explicite.
A68: US4.3-SC01 | B68: Agrégation temporelle | C68: EPIC 4 – Calcul d'indicateurs | D68: US4.3 | E68: Agrégation temporelle | F68: True | G68: Backend | H68: Gestion des données & catalogue | I68: US1.6 ; US4.1 ; US6.24 | J68: Exploitation | K68: Pilier 2 – Diagnostic & Analyse multicritère (+ Pilier 3) | L68: Administrateur expert data | M68: En tant qu'administrateur expert data, je veux agréger les données dans le temps afin de produire des séries comparables. | N68: Étant donné des données historisées (US1.6), Quand l'agrégation temporelle (mensuelle, annuelle, pluriannuelle) est exécutée, Alors les séries consolidées sont produites sur les périodes demandées, Et les données sous-jacentes restent disponibles.
A69: US4.3-SC02 | B69: Taux de couverture et reproductibilité | C69: EPIC 4 – Calcul d'indicateurs | D69: US4.3 | E69: Agrégation temporelle | F69: True | G69: Backend | H69: Gestion des données & catalogue | I69: US1.6 ; US4.1 ; US6.24 | J69: Exploitation | K69: Pilier 2 – Diagnostic & Analyse multicritère (+ Pilier 3) | L69: Administrateur expert data | M69: En tant qu'administrateur expert data, je veux agréger les données dans le temps afin de produire des séries comparables. | N69: Étant donné une période contenant des données manquantes, Quand le résultat est produit, Alors le taux de couverture de la période est indiqué, Et le résultat est marqué si le seuil de complétude n'est pas atteint. - Quand la même agrégation est relancée sur la même période et les mêmes données, Alors le résultat est identique (reproductibilité des calculs).
A70: US4.3-SC03 | B70: Limitation à l'historique disponible | C70: EPIC 4 – Calcul d'indicateurs | D70: US4.3 | E70: Agrégation temporelle | F70: True | G70: Backend | H70: Gestion des données & catalogue | I70: US1.6 ; US4.1 ; US6.24 | J70: Exploitation | K70: Pilier 2 – Diagnostic & Analyse multicritère (+ Pilier 3) | L70: Administrateur expert data | M70: En tant qu'administrateur expert data, je veux agréger les données dans le temps afin de produire des séries comparables. | N70: Étant donné une période demandée dépassant l'historique disponible, Quand l'agrégation est exécutée, Alors elle est limitée à l'historique existant et l'écart est signalé, ou refusée si aucune donnée ne couvre la période. - Quand un indicateur est produit à plusieurs granularités temporelles, Alors le périmètre de calcul (données incluses, période couverte) est documenté pour garantir la comparabilité des séries.
A71: US4.5-SC01 | B71: Filtrage des données pour le calcul | C71: EPIC 4 – Calcul d'indicateurs | D71: US4.5 | E71: Filtrer les données | F71: True | G71: Front-end | H71: Gestion des données & catalogue | J71: Exploitation | K71: Pilier 2 – Diagnostic & Analyse multicritère (+ Pilier 3) | L71: Administrateur expert data | M71: En tant qu'administrateur expert data, je veux filtrer les données afin de restreindre le calcul aux valeurs pertinentes. | N71: Étant donné l'interface de calcul d'un indicateur, Quand l'administrateur applique des filtres (période, source, qualité, territoire : captage, BVAEP, commune), Alors seules les valeurs répondant aux filtres sont utilisées dans le calcul, Et les filtres appliqués sont affichés à l'écran. - Quand l'administrateur exclut les données de qualité insuffisante (fiabilité faible, anomalies, sous le seuil de complétude), Alors elles sont exclues du calcul, Et l'option d'exclusion est visible dans l'interface. - Quand les filtres sont modifiés, Alors le calcul est relancé sur le nouveau périmètre, Et aucun résultat obsolète n'est affiché sans mention.
A72: US4.5-SC02 | B72: Refus sans données répondant aux filtres | C72: EPIC 4 – Calcul d'indicateurs | D72: US4.5 | E72: Filtrer les données | F72: True | G72: Front-end | H72: Gestion des données & catalogue | J72: Exploitation | K72: Pilier 2 – Diagnostic & Analyse multicritère (+ Pilier 3) | L72: Administrateur expert data | M72: En tant qu'administrateur expert data, je veux filtrer les données afin de restreindre le calcul aux valeurs pertinentes. | N72: Étant donné une combinaison de filtres ne sélectionnant aucune donnée, Quand le calcul est demandé, Alors il est refusé avec le message « aucun jeu de données ne correspond aux filtres appliqués ». - Quand l'administrateur consulte la configuration du calcul, Alors il voit un résumé des critères retenus (période, sources, territoires, seuil de qualité) avant exécution.
A73: US6.1-SC01 | B73: Affichage de la carte interactive | C73: EPIC 6 – Visualisation | D73: US6.1 | E73: Visualiser sur carte | F73: True | G73: Front-end | H73: Cartographie & exploration > Cartographie | J73: Restitution – Diffusion | K73: Pilier 4 – Partage & Diffusion | L73: Intéressé public | M73: En tant qu'intéressé public, je veux visualiser les données sur carte afin de situer les territoires concernés. | N73: Étant donné la plateforme opérationnelle avec des données BVAEP et captages chargées, quand je consulte la vue « Carte », alors une carte interactive s'affiche (fond Cartographique par défaut) avec les objets du périmètre positionnés.
A74: US6.1-SC02 | B74: Navigation par pan et zoom | C74: EPIC 6 – Visualisation | D74: US6.1 | E74: Visualiser sur carte | F74: True | G74: Front-end | H74: Cartographie & exploration > Cartographie | J74: Restitution – Diffusion | K74: Pilier 4 – Partage & Diffusion | L74: Intéressé public | M74: En tant qu'intéressé public, je veux visualiser les données sur carte afin de situer les territoires concernés. | N74: Étant donné une carte affichée, quand je me déplace (pan) ou je zoome, alors l'emprise se met à jour et les objets pertinents apparaissent, sans rechargement de la page.
A75: US6.1-SC03 | B75: Infobulle au survol d'un objet | C75: EPIC 6 – Visualisation | D75: US6.1 | E75: Visualiser sur carte | F75: True | G75: Front-end | H75: Cartographie & exploration > Cartographie | J75: Restitution – Diffusion | K75: Pilier 4 – Partage & Diffusion | L75: Intéressé public | M75: En tant qu'intéressé public, je veux visualiser les données sur carte afin de situer les territoires concernés. | N75: Étant donné un objet visible (BVAEP, captage, PPE), quand je le survole, alors une infobulle présente son nom et son identifiant.
A76: US6.1-SC04 | B76: Affichage d'une zone sans donnée | C76: EPIC 6 – Visualisation | D76: US6.1 | E76: Visualiser sur carte | F76: True | G76: Front-end | H76: Cartographie & exploration > Cartographie | J76: Restitution – Diffusion | K76: Pilier 4 – Partage & Diffusion | L76: Intéressé public | M76: En tant qu'intéressé public, je veux visualiser les données sur carte afin de situer les territoires concernés. | N76: Étant donné une zone sans donnée dans l'emprise, quand la carte est rendue, alors le périmètre reste lisible avec un libellé explicite (pas de fond vide ambigu).
A77: US6.2-SC01 | B77: Colorisation carto selon l'indicateur | C77: EPIC 6 – Visualisation | D77: US6.2 | E77: Afficher indicateurs carto | F77: True | G77: Front-end | H77: Cartographie & exploration > Cartographie | I77: US3.5 | J77: Restitution – Diffusion | K77: Pilier 4 – Partage & Diffusion | L77: Intéressé public | M77: En tant qu'intéressé public, je veux afficher les indicateurs sur la carte afin d'en lire la répartition géographique. | N77: Étant donné un indicateur sélectionné dans le volet indicateurs, quand je l'applique à la carte, alors les unités sont colorées selon les classes de valeurs de l'indicateur, avec une légende affichant la plage et les couleurs.
A78: US6.2-SC02 | B78: Classe « sans donnée » | C78: EPIC 6 – Visualisation | D78: US6.2 | E78: Afficher indicateurs carto | F78: True | G78: Front-end | H78: Cartographie & exploration > Cartographie | I78: US3.5 | J78: Restitution – Diffusion | K78: Pilier 4 – Partage & Diffusion | L78: Intéressé public | M78: En tant qu'intéressé public, je veux afficher les indicateurs sur la carte afin d'en lire la répartition géographique. | N78: Étant donné une unité sans valeur pour l'indicateur, quand la carte est rendue, alors cette unité est affectée à une classe « sans donnée » distincte, hors plage de valeurs.
A79: US6.2-SC03 | B79: Rafraîchissement du rendu cartographique | C79: EPIC 6 – Visualisation | D79: US6.2 | E79: Afficher indicateurs carto | F79: True | G79: Front-end | H79: Cartographie & exploration > Cartographie | I79: US3.5 | J79: Restitution – Diffusion | K79: Pilier 4 – Partage & Diffusion | L79: Intéressé public | M79: En tant qu'intéressé public, je veux afficher les indicateurs sur la carte afin d'en lire la répartition géographique. | N79: Étant donné un indicateur calculé ou recalculé, quand je rafraîchis le rendu cartographique, alors les couleurs correspondent aux nouvelles valeurs sans référence obsolète.
A80: US6.2-SC04 | B80: Bascule immédiate de l'indicateur | C80: EPIC 6 – Visualisation | D80: US6.2 | E80: Afficher indicateurs carto | F80: True | G80: Front-end | H80: Cartographie & exploration > Cartographie | I80: US3.5 | J80: Restitution – Diffusion | K80: Pilier 4 – Partage & Diffusion | L80: Intéressé public | M80: En tant qu'intéressé public, je veux afficher les indicateurs sur la carte afin d'en lire la répartition géographique. | N80: Étant donné un changement d'indicateur (via Famille → Thème → Groupe), quand je bascule, alors la légende et les couleurs correspondent immédiatement au nouvel indicateur en conservant la sélection courante.
A81: US6.3-SC01 | B81: Synchronisation du zoom et des unités | C81: EPIC 6 – Visualisation | D81: US6.3 | E81: Navigation (zoom filtres) | F81: True | G81: Front-end | H81: Cartographie & exploration > Cartographie | J81: Restitution – Diffusion | K81: Pilier 4 – Partage & Diffusion | L81: Intéressé public | M81: En tant qu'intéressé public, je veux naviguer sur la carte afin d'explorer librement le territoire. | N81: Étant donné la carte, quand j'utilise les contrôles de zoom et le pan, alors l'emprise évolue et les unités affichées sont recalculées de façon synchrone.
A82: US6.3-SC02 | B82: Préservation des filtres à la navigation | C82: EPIC 6 – Visualisation | D82: US6.3 | E82: Navigation (zoom filtres) | F82: True | G82: Front-end | H82: Cartographie & exploration > Cartographie | J82: Restitution – Diffusion | K82: Pilier 4 – Partage & Diffusion | L82: Intéressé public | M82: En tant qu'intéressé public, je veux naviguer sur la carte afin d'explorer librement le territoire. | N82: Étant donné une sélection ou des filtres actifs, quand je navigue sur la carte, alors la sélection et les filtres ne sont ni réinitialisés ni altérés.
A83: US6.3-SC03 | B83: Réinitialisation de la vue | C83: EPIC 6 – Visualisation | D83: US6.3 | E83: Navigation (zoom filtres) | F83: True | G83: Front-end | H83: Cartographie & exploration > Cartographie | J83: Restitution – Diffusion | K83: Pilier 4 – Partage & Diffusion | L83: Intéressé public | M83: En tant qu'intéressé public, je veux naviguer sur la carte afin d'explorer librement le territoire. | N83: Étant donné une navigation avancée, quand j'actionne la réinitialisation de la vue, alors l'emprise revient au périmètre par défaut en conservant les filtres utilisateur.
A84: US6.3-SC04 | B84: Regroupement des unités | C84: EPIC 6 – Visualisation | D84: US6.3 | E84: Navigation (zoom filtres) | F84: True | G84: Front-end | H84: Cartographie & exploration > Cartographie | J84: Restitution – Diffusion | K84: Pilier 4 – Partage & Diffusion | L84: Intéressé public | M84: En tant qu'intéressé public, je veux naviguer sur la carte afin d'explorer librement le territoire. | N84: Étant donné un changement d'échelle, quand les unités deviennent trop nombreuses à l'écran, alors la carte propose un regroupement lisible (agrégation visuelle) sans perte de données.
A85: US6.4-SC01 | B85: Tracé de la série chronologique | C85: EPIC 6 – Visualisation | D85: US6.4 | E85: Graphiques temporels | F85: True | G85: Front-end | H85: Cartographie & exploration > Visualisation & dataviz | I85: US6.7 | J85: Restitution – Diffusion | K85: Pilier 4 – Partage & Diffusion | L85: Expert métier eau potable | M85: En tant qu'expert métier eau potable, je veux consulter l'évolution temporelle des indicateurs afin d'identifier les dynamiques impactant la ressource. | N85: Étant donné un indicateur à données historisées, quand je consulte son graphique temporel, alors une série chronologique est tracée avec unité, dates et période affichées.
A86: US6.4-SC02 | B86: Séries distinctes par palette | C86: EPIC 6 – Visualisation | D86: US6.4 | E86: Graphiques temporels | F86: True | G86: Front-end | H86: Cartographie & exploration > Visualisation & dataviz | I86: US6.7 | J86: Restitution – Diffusion | K86: Pilier 4 – Partage & Diffusion | L86: Expert métier eau potable | M86: En tant qu'expert métier eau potable, je veux consulter l'évolution temporelle des indicateurs afin d'identifier les dynamiques impactant la ressource. | N86: Étant donné plusieurs unités sélectionnées (captages et/ou BVAEP), quand le graphique temporel est affiché, alors chaque série est identifiée et distinguée par une palette de couleurs cohérente avec la carte.
A87: US6.4-SC03 | B87: Affichage d'une lacune de mesure | C87: EPIC 6 – Visualisation | D87: US6.4 | E87: Graphiques temporels | F87: True | G87: Front-end | H87: Cartographie & exploration > Visualisation & dataviz | I87: US6.7 | J87: Restitution – Diffusion | K87: Pilier 4 – Partage & Diffusion | L87: Expert métier eau potable | M87: En tant qu'expert métier eau potable, je veux consulter l'évolution temporelle des indicateurs afin d'identifier les dynamiques impactant la ressource. | N87: Étant donné une période sans mesure, quand elle appartient à la série, alors elle apparaît comme une lacune explicite (valeur indisponible), jamais remplacée par un zéro.
A88: US6.4-SC04 | B88: Infobulle sur un point de la série | C88: EPIC 6 – Visualisation | D88: US6.4 | E88: Graphiques temporels | F88: True | G88: Front-end | H88: Cartographie & exploration > Visualisation & dataviz | I88: US6.7 | J88: Restitution – Diffusion | K88: Pilier 4 – Partage & Diffusion | L88: Expert métier eau potable | M88: En tant qu'expert métier eau potable, je veux consulter l'évolution temporelle des indicateurs afin d'identifier les dynamiques impactant la ressource. | N88: Étant donné un point de la série, quand je le survole, alors une infobulle affiche la date et la valeur de l'indicateur.
A89: US6.7-SC01 | B89: Consultation d'une fiche territoire | C89: EPIC 6 – Visualisation | D89: US6.7 | E89: Fiche territoire | F89: True | G89: Front-end | H89: Cartographie & exploration > Fiches & synthèse territoriale | J89: Restitution – Diffusion | K89: Pilier 4 – Partage & Diffusion | L89: Décideur métier | M89: En tant que décideur métier, je veux consulter une fiche territoire afin d'avoir une synthèse d'un bassin versant. | N89: Étant donné une fiche territoire (commune, BVAEP ou bassin versant), quand je la consulte, alors elle présente le périmètre décrit, les unités de gestion associées et les indicateurs disponibles.
A90: US6.7-SC02 | B90: Contenu strictement issu des données | C90: EPIC 6 – Visualisation | D90: US6.7 | E90: Fiche territoire | F90: True | G90: Front-end | H90: Cartographie & exploration > Fiches & synthèse territoriale | J90: Restitution – Diffusion | K90: Pilier 4 – Partage & Diffusion | L90: Décideur métier | M90: En tant que décideur métier, je veux consulter une fiche territoire afin d'avoir une synthèse d'un bassin versant. | N90: Étant donné une fiche territoire générée, quand elle est affichée, alors son contenu est strictement issu des données et indicateurs produits, sans ajout interprétatif ni classement/priorisation.
A91: US6.7-SC03 | B91: Ouverture de la fiche depuis la carte | C91: EPIC 6 – Visualisation | D91: US6.7 | E91: Fiche territoire | F91: True | G91: Front-end | H91: Cartographie & exploration > Fiches & synthèse territoriale | J91: Restitution – Diffusion | K91: Pilier 4 – Partage & Diffusion | L91: Décideur métier | M91: En tant que décideur métier, je veux consulter une fiche territoire afin d'avoir une synthèse d'un bassin versant. | N91: Étant donné une unité cartographique, quand je l'active (clic ou sélection), alors je peux ouvrir sa fiche territoire depuis la carte.
A92: US6.7-SC04 | B92: Reflet de la dernière version | C92: EPIC 6 – Visualisation | D92: US6.7 | E92: Fiche territoire | F92: True | G92: Front-end | H92: Cartographie & exploration > Fiches & synthèse territoriale | J92: Restitution – Diffusion | K92: Pilier 4 – Partage & Diffusion | L92: Décideur métier | M92: En tant que décideur métier, je veux consulter une fiche territoire afin d'avoir une synthèse d'un bassin versant. | N92: Étant donné une donnée source mise à jour, quand la fiche est consultée, alors elle reflète la dernière version sans action manuelle.
A93: US6.8-SC01 | B93: Bascule d'échelle captages/bassins versants | C93: EPIC 6 – Visualisation | D93: US6.8 | E93: Basculer l'échelle d'analyse Captages ↔ Bassins versants | F93: True | G93: Front-end | H93: Cartographie & exploration > Cartographie | I93: US3.1 ; US3.2 | J93: Restitution – Diffusion | K93: Pilier 4 – Partage & Diffusion | L93: Administrateur expert data | M93: En tant qu'administrateur expert data, je veux basculer l'échelle d'analyse entre captages et bassins versants afin de changer de niveau de lecture. | N93: Étant donné une échelle active (captages ou BVAEP), quand je bascule l'échelle, alors la carte affiche immédiatement les unités de la nouvelle échelle sur la même emprise.
A94: US6.8-SC02 | B94: Mémorisation indépendante des sélections | C94: EPIC 6 – Visualisation | D94: US6.8 | E94: Basculer l'échelle d'analyse Captages ↔ Bassins versants | F94: True | G94: Front-end | H94: Cartographie & exploration > Cartographie | I94: US3.1 ; US3.2 | J94: Restitution – Diffusion | K94: Pilier 4 – Partage & Diffusion | L94: Administrateur expert data | M94: En tant qu'administrateur expert data, je veux basculer l'échelle d'analyse entre captages et bassins versants afin de changer de niveau de lecture. | N94: Étant donné des sélections distinctes Captages et Bassins versants, quand j'alterne les échelles, alors chaque sélection est rappelée indépendamment (les types d'unités ne sont pas mélangés).
A95: US6.8-SC03 | B95: Agrégation selon l'échelle active | C95: EPIC 6 – Visualisation | D95: US6.8 | E95: Basculer l'échelle d'analyse Captages ↔ Bassins versants | F95: True | G95: Front-end | H95: Cartographie & exploration > Cartographie | I95: US3.1 ; US3.2 | J95: Restitution – Diffusion | K95: Pilier 4 – Partage & Diffusion | L95: Administrateur expert data | M95: En tant qu'administrateur expert data, je veux basculer l'échelle d'analyse entre captages et bassins versants afin de changer de niveau de lecture. | N95: Étant donné un indicateur applicable aux deux échelles, quand je bascule, alors la valeur affichée correspond à l'agrégation de l'échelle active (globale pour un BVAEP, ponctuelle pour un captage).
A96: US6.8-SC04 | B96: Mise à jour du compteur à la bascule | C96: EPIC 6 – Visualisation | D96: US6.8 | E96: Basculer l'échelle d'analyse Captages ↔ Bassins versants | F96: True | G96: Front-end | H96: Cartographie & exploration > Cartographie | I96: US3.1 ; US3.2 | J96: Restitution – Diffusion | K96: Pilier 4 – Partage & Diffusion | L96: Administrateur expert data | M96: En tant qu'administrateur expert data, je veux basculer l'échelle d'analyse entre captages et bassins versants afin de changer de niveau de lecture. | N96: Étant donné le compteur d'unités, quand je bascule d'échelle, alors il reflète immédiatement le nombre d'unités sélectionnées à la nouvelle échelle.
A97: US6.9-SC01 | B97: Affichage du compteur d'unités sélectionnées | C97: EPIC 6 – Visualisation | D97: US6.9 | E97: Afficher le compteur d'unités sélectionnées | F97: True | G97: Front-end | H97: Cartographie & exploration > Outils d'exploration | J97: Restitution – Diffusion | K97: Pilier 4 – Partage & Diffusion | L97: Intéressé public | M97: En tant qu'intéressé public, je veux afficher le compteur d'unités sélectionnées afin de connaître le périmètre courant. | N97: Étant donné une sélection en cours, quand la vue est chargée, alors un compteur affiche le nombre d'unités sélectionnées, au format « X captages · Y bassins versants ».
A98: US6.9-SC02 | B98: Mise à jour temps réel du compteur | C98: EPIC 6 – Visualisation | D98: US6.9 | E98: Afficher le compteur d'unités sélectionnées | F98: True | G98: Front-end | H98: Cartographie & exploration > Outils d'exploration | J98: Restitution – Diffusion | K98: Pilier 4 – Partage & Diffusion | L98: Intéressé public | M98: En tant qu'intéressé public, je veux afficher le compteur d'unités sélectionnées afin de connaître le périmètre courant. | N98: Étant donné une action d'ajout ou de retrait de sélection, quand elle est validée, alors le compteur se met à jour en temps réel.
A99: US6.9-SC03 | B99: Compteur à zéro pour une sélection vide | C99: EPIC 6 – Visualisation | D99: US6.9 | E99: Afficher le compteur d'unités sélectionnées | F99: True | G99: Front-end | H99: Cartographie & exploration > Outils d'exploration | J99: Restitution – Diffusion | K99: Pilier 4 – Partage & Diffusion | L99: Intéressé public | M99: En tant qu'intéressé public, je veux afficher le compteur d'unités sélectionnées afin de connaître le périmètre courant. | N99: Étant donné une sélection vide, quand la vue est affichée, alors le compteur est à 0 avec un message invitant à sélectionner (aucune ambiguïté entre « rien » et « tout »).
A100: US6.9-SC04 | B100: Cohérence carte/listes/compteur | C100: EPIC 6 – Visualisation | D100: US6.9 | E100: Afficher le compteur d'unités sélectionnées | F100: True | G100: Front-end | H100: Cartographie & exploration > Outils d'exploration | J100: Restitution – Diffusion | K100: Pilier 4 – Partage & Diffusion | L100: Intéressé public | M100: En tant qu'intéressé public, je veux afficher le compteur d'unités sélectionnées afin de connaître le périmètre courant. | N100: Étant donné la carte, les listes et le compteur, quand une sélection est modifiée, alors ils restent cohérents entre eux.
A101: US6.10-SC01 | B101: Suggestions de recherche | C101: EPIC 6 – Visualisation | D101: US6.10 | E101: Rechercher avec suggestions (commune, province, captage, presets) | F101: True | G101: Front-end | H101: Cartographie & exploration > Sélecteur de captages / BV | J101: Restitution – Diffusion | K101: Pilier 4 – Partage & Diffusion | L101: Intéressé public | M101: En tant qu'intéressé public, je veux rechercher avec des suggestions afin de trouver rapidement un captage ou une commune. | N101: Étant donné la zone de recherche, quand je saisis au moins deux caractères, alors des suggestions s'affichent pour : communes, provinces, captages, BVAEP et presets « Top 10 ».
A102: US6.10-SC02 | B102: Recherche insensible à la casse et aux accents | C102: EPIC 6 – Visualisation | D102: US6.10 | E102: Rechercher avec suggestions (commune, province, captage, presets) | F102: True | G102: Front-end | H102: Cartographie & exploration > Sélecteur de captages / BV | J102: Restitution – Diffusion | K102: Pilier 4 – Partage & Diffusion | L102: Intéressé public | M102: En tant qu'intéressé public, je veux rechercher avec des suggestions afin de trouver rapidement un captage ou une commune. | N102: Étant donné un nom saisi, quand la recherche ignore la casse et les accents, alors les résultats attendus sont retrouvés.
A103: US6.10-SC03 | B103: Centrage sur l'entité choisie | C103: EPIC 6 – Visualisation | D103: US6.10 | E103: Rechercher avec suggestions (commune, province, captage, presets) | F103: True | G103: Front-end | H103: Cartographie & exploration > Sélecteur de captages / BV | J103: Restitution – Diffusion | K103: Pilier 4 – Partage & Diffusion | L103: Intéressé public | M103: En tant qu'intéressé public, je veux rechercher avec des suggestions afin de trouver rapidement un captage ou une commune. | N103: Étant donné le choix d'une suggestion commune ou province, quand je valide, alors la carte se centre sur l'entité et la sélection est restreinte à son périmètre (filtre géographique).
A104: US6.10-SC04 | B104: Message « Aucun résultat » | C104: EPIC 6 – Visualisation | D104: US6.10 | E104: Rechercher avec suggestions (commune, province, captage, presets) | F104: True | G104: Front-end | H104: Cartographie & exploration > Sélecteur de captages / BV | J104: Restitution – Diffusion | K104: Pilier 4 – Partage & Diffusion | L104: Intéressé public | M104: En tant qu'intéressé public, je veux rechercher avec des suggestions afin de trouver rapidement un captage ou une commune. | N104: Étant donné une recherche sans résultat, quand elle est exécutée, alors un message « Aucun résultat » est affiché, sans rechargement ni erreur.
A105: US6.11-SC01 | B105: Cumul de facettes de recherche | C105: EPIC 6 – Visualisation | D105: US6.11 | E105: Cumuler plusieurs facettes de recherche (sélection multiple) | F105: True | G105: Front-end | H105: Cartographie & exploration > Sélecteur de captages / BV | J105: Restitution – Diffusion | K105: Pilier 4 – Partage & Diffusion | L105: Intéressé public | M105: En tant qu'intéressé public, je veux cumuler plusieurs facettes de recherche afin d'affiner ma sélection. | N105: Étant donné plusieurs facettes (commune, province, type d'unité, indicateur), quand je les cumule, alors la sélection résultante est la combinaison des critères définie (intersection des filtres).
A106: US6.11-SC02 | B106: Cohérence carte/listes/compteur | C106: EPIC 6 – Visualisation | D106: US6.11 | E106: Cumuler plusieurs facettes de recherche (sélection multiple) | F106: True | G106: Front-end | H106: Cartographie & exploration > Sélecteur de captages / BV | J106: Restitution – Diffusion | K106: Pilier 4 – Partage & Diffusion | L106: Intéressé public | M106: En tant qu'intéressé public, je veux cumuler plusieurs facettes de recherche afin d'affiner ma sélection. | N106: Étant donné un filtre et une sélection manuelle combinés, quand la vue est rendue, alors la carte, les listes et le compteur reflètent exactement la même combinaison.
A107: US6.11-SC03 | B107: État « filtre incompatible » | C107: EPIC 6 – Visualisation | D107: US6.11 | E107: Cumuler plusieurs facettes de recherche (sélection multiple) | F107: True | G107: Front-end | H107: Cartographie & exploration > Sélecteur de captages / BV | J107: Restitution – Diffusion | K107: Pilier 4 – Partage & Diffusion | L107: Intéressé public | M107: En tant qu'intéressé public, je veux cumuler plusieurs facettes de recherche afin d'affiner ma sélection. | N107: Étant donné des facettes cumulées méthodologiquement incompatibles, quand je tente de les cumuler, alors le système présente un état « filtre incompatible » explicite, sans ambiguïté.
A108: US6.11-SC04 | B108: Restauration de l'état des facettes | C108: EPIC 6 – Visualisation | D108: US6.11 | E108: Cumuler plusieurs facettes de recherche (sélection multiple) | F108: True | G108: Front-end | H108: Cartographie & exploration > Sélecteur de captages / BV | J108: Restitution – Diffusion | K108: Pilier 4 – Partage & Diffusion | L108: Intéressé public | M108: En tant qu'intéressé public, je veux cumuler plusieurs facettes de recherche afin d'affiner ma sélection. | N108: Étant donné l'état courant des facettes, quand je quitte puis reviens sur la vue, alors l'état est restauré ou clairement signalé comme non conservé.
... A131: US6.17-SC04 | B131: Recalcul de l'ordre en conservant le mode | C131: EPIC 6 – Visualisation | D131: US6.17 | E131: Trier la liste (distance / nom) | F131: True | G131: Front-end | H131: Cartographie & exploration > Sélecteur de captages / BV | J131: Restitution – Diffusion | K131: Pilier 4 – Partage & Diffusion | L131: Intéressé public | M131: En tant qu'intéressé public, je veux trier la liste par distance ou par nom afin d'organiser ma lecture. | N131: Étant donné un tri appliqué, quand j'ajoute ou je retire des unités, alors l'ordre est recalculé en conservant le mode choisi.
A132: US6.18-SC01 | B132: Calcul des communes intersectant un BV (≥20 %) | C132: EPIC 6 – Visualisation | D132: US6.18 | E132: Calculer les communes intersectant un BV (≥ 20 %) pour la facette Commune | F132: True | G132: Backend | H132: Cartographie & exploration > Sélecteur de captages / BV | I132: US3.1 ; US3.2 | J132: Restitution – Diffusion | K132: Pilier 4 – Partage & Diffusion | L132: Administrateur expert data | M132: En tant qu'administrateur expert data, je veux calculer les communes intersectant un bassin versant afin d'alimenter la facette Commune. | N132: Étant donné un bassin versant et le référentiel communal, quand le calcul d'intersection est exécuté, alors sont identifiées les communes dont la surface intersectée avec le bassin versant atteint au moins 20 % de la surface du bassin.
A133: US6.18-SC02 | B133: Exclusion sous le seuil de 20 % | C133: EPIC 6 – Visualisation | D133: US6.18 | E133: Calculer les communes intersectant un BV (≥ 20 %) pour la facette Commune | F133: True | G133: Backend | H133: Cartographie & exploration > Sélecteur de captages / BV | I133: US3.1 ; US3.2 | J133: Restitution – Diffusion | K133: Pilier 4 – Partage & Diffusion | L133: Administrateur expert data | M133: En tant qu'administrateur expert data, je veux calculer les communes intersectant un bassin versant afin d'alimenter la facette Commune. | N133: Étant donné une commune dont le taux d'intersection est inférieur au seuil de 20 %, quand le calcul est exécuté, alors elle n'est pas retenue pour la facette « Commune ».
A134: US6.18-SC03 | B134: Recalcul après mise à jour du référentiel | C134: EPIC 6 – Visualisation | D134: US6.18 | E134: Calculer les communes intersectant un BV (≥ 20 %) pour la facette Commune | F134: True | G134: Backend | H134: Cartographie & exploration > Sélecteur de captages / BV | I134: US3.1 ; US3.2 | J134: Restitution – Diffusion | K134: Pilier 4 – Partage & Diffusion | L134: Administrateur expert data | M134: En tant qu'administrateur expert data, je veux calculer les communes intersectant un bassin versant afin d'alimenter la facette Commune. | N134: Étant donné un bassin versant mis à jour (US3.1), quand le calcul est relancé, alors la liste des communes de la facette reflète les relations à jour du référentiel.
A135: US6.18-SC04 | B135: Alimentation de la facette Commune | C135: EPIC 6 – Visualisation | D135: US6.18 | E135: Calculer les communes intersectant un BV (≥ 20 %) pour la facette Commune | F135: True | G135: Backend | H135: Cartographie & exploration > Sélecteur de captages / BV | I135: US3.1 ; US3.2 | J135: Restitution – Diffusion | K135: Pilier 4 – Partage & Diffusion | L135: Administrateur expert data | M135: En tant qu'administrateur expert data, je veux calculer les communes intersectant un bassin versant afin d'alimenter la facette Commune. | N135: Étant donné la facette « Commune » de la recherche (US6.10), quand elle est alimentée par ce calcul, alors elle ne présente que les communes validées par la règle (≥ 20 %), cohérentes avec la sélection courante des bassins versants.
A136: US6.18-SC05 | B136: Recalcul rejouable des paramètres | C136: EPIC 6 – Visualisation | D136: US6.18 | E136: Calculer les communes intersectant un BV (≥ 20 %) pour la facette Commune | F136: True | G136: Backend | H136: Cartographie & exploration > Sélecteur de captages / BV | I136: US3.1 ; US3.2 | J136: Restitution – Diffusion | K136: Pilier 4 – Partage & Diffusion | L136: Administrateur expert data | M136: En tant qu'administrateur expert data, je veux calculer les communes intersectant un bassin versant afin d'alimenter la facette Commune. | N136: Étant donné un calcul exécuté, quand le seuil ou le référentiel ont été modifiés, alors le recalcul est rejouable et trace les paramètres utilisés (seuil, version du référentiel), sans saisie manuelle.
...
